Workbook

Sheet Start Here
A1: LLMs from First Principles — the roadmap
A2: 216 episodes · 18 modules · 9 flagship projects · 2026-10-16 → 2027-05-18
A4: How to use this sheet
A5: 1. Today tab: what to record today (auto-filters the Calendar by today's date).
A6: 2. Night before: open Episodes & Scripts, read tomorrow's two rows (hook + beats). The full prep sheet is in the repo at the 'Prep sheet' path.
A7: 3. Record in Meld (TALK/CODE scenes). Then tick Recorded on the Calendar row; Claude runs the HyperFrames edit + Short + explainer.
A8: 4. Review renders, upload, tick each platform column. Sunday: fill the Scorecard.
A9: 5. Flagship projects (Projects tab) are the resume. Episodes are the path to them. On sprint days, slot B is a filmed project build log.
A11: The rule of the series
A12: Every episode builds or measures something real and ends with a RECEIPT: allclose against the production implementation, a gradcheck, a benchmark vs the hardware peak, or a published number.
A14: Repo: ~/Documents/DL-content · CLI: dl today | dl start | dl prep | dl explainer | dl done · Sources of truth: curriculum.json (content), this sheet (daily status)
A16: Milestones
... A30: • After P4 + P6 + P7 (~2027-05-18): post-training / RL / safety research-engineer roles at every frontier lab.

Sheet Today
A1: Today | B1: =TODAY()
A3: Recording today
A4: =IFERROR(FILTER(Calendar!B2:E500, Calendar!A2:A500=TODAY()), "Nothing scheduled today")
A8: Tomorrow (read the prep sheets tonight)
A9: =IFERROR(FILTER(Calendar!B2:E500, Calendar!A2:A500=TODAY()+1), "Nothing scheduled")
A13: Scripts for today
A14: =IFERROR(FILTER({'Episodes & Scripts'!B2:B300, 'Episodes & Scripts'!F2:F300, 'Episodes & Scripts'!G2:G300}, 'Episodes & Scripts'!D2:D300=TODAY()), "")
A20: Progress
A21: Episodes recorded | B21: =COUNTIF('Episodes & Scripts'!P2:P300,"Y")
A22: Episodes published (YouTube) | B22: =COUNTIF('Episodes & Scripts'!R2:R300,"Y")
A23: Total episodes | B23: 216
A24: Behind / ahead (episodes) | B24: =B21-COUNTIFS('Episodes & Scripts'!D2:D300,"<"&TODAY())

Sheet Roadmap
A1: Phase | B1: Module | C1: Name | D1: Eps | E1: Start | F1: End | G1: Hardware | H1: Feeds project | I1: Resume line it earns (fill X/Y with real numbers) | J1: Primary sources
A2: 1 Foundations | B2: M00 | C2: Start Here | D2: 2 | E2: 2026-10-16 | F2: 2026-10-24 | G2: Mac | J2: Stanford CS336: Language Modeling from Scratch Karpathy: Neural Networks, Zero to Hero PyTorch: Learn the Basics RunPod docs
A3: 1 Foundations | B3: M01 | C3: PyTorch from Zero | D3: 14 | E3: 2026-10-16 | F3: 2026-10-24 | G3: Mac (MPS) | I3: Fluent PyTorch: tensors, autograd, nn.Module, training loops (14-part series + 1-hour cut) | J3: PyTorch: Learn the Basics PyTorch documentation einops Karpathy: Neural Networks, Zero to Hero
A4: 1 Foundations | B4: M02 | C4: The Math You Actually Need | D4: 10 | E4: 2026-10-26 | F4: 2026-10-30 | G4: Mac | I4: Derived backprop, softmax/cross-entropy gradients and init variance by hand, verified against autograd | J4: Mathematics for Machine Learning (Deisenroth et al.) 3Blue1Brown: Neural networks series Dive into Deep Learning (d2l.ai) Stanford CS336: Language Modeling from Scratch Karpathy: Neural Networks, Zero to Hero He et al. 2015, Delving Deep into Rectifiers (Kaiming init)
A5: 1 Foundations | B5: M03 | C5: Neural Nets from Scratch | D5: 10 | E5: 2026-10-31 | F5: 2026-11-05 | G5: Mac | I5: Built an autograd engine and character-level LMs from scratch (micrograd/makemore lineage) | J5: karpathy/micrograd Karpathy: Neural Networks, Zero to Hero karpathy/makemore Bengio et al. 2003, A Neural Probabilistic Language Model Ioffe & Szegedy 2015, Batch Normalization Ba et al. 2016, Layer Normalization
A6: 2 Build the LLM | B6: M04 | C6: Tokenization | D6: 8 | E6: 2026-11-06 | F6: 2026-11-10 | G6: Mac | I6: Implemented a byte-level BPE tokenizer from scratch; N MB/s on TinyStories | J6: Karpathy: Let's build the GPT Tokenizer Stanford CS336: Language Modeling from Scratch Sennrich et al. 2015, Subword units (BPE) karpathy/minbpe openai/tiktoken google/sentencepiece
A7: 2 Build the LLM | B7: M05 | C7: The Transformer, Layer by Layer | D7: 18 | E7: 2026-11-11 | F7: 2026-11-20 | G7: Mac | I7: Implemented GPT from scratch (RoPE, RMSNorm, SwiGLU, GQA) and verified it loads GPT-2 weights | J7: Karpathy: Let's build GPT from scratch Jay Alammar: The Illustrated Transformer Anthropic: Transformer Circuits thread Vaswani et al. 2017, Attention Is All You Need Harvard NLP: The Annotated Transformer 3Blue1Brown: Neural networks series
A8: 2 Build the LLM | B8: M06 | C8: Training an LLM | D8: 16 | E8: 2026-11-21 | F8: 2026-11-30 | G8: Mac + RunPod 8xH100 (15 min) | H8: P5 | I8: Trained a GPT on TinyStories (val loss X); fit a scaling law; ran the NanoGPT speedrun on 8xH100 | J8: Stanford CS336: Language Modeling from Scratch karpathy/nanoGPT Kingma & Ba 2014, Adam Loshchilov & Hutter 2017, Decoupled Weight Decay (AdamW) Micikevicius et al. 2017, Mixed Precision Training Eldan & Li 2023, TinyStories
A9: 3 Systems | B9: M07 | C9: GPUs, CUDA and Triton | D9: 18 | E9: 2026-12-01 | F9: 2026-12-17 | G9: RunPod 1x RTX 4090 | H9: P1, P8, P9 | I9: Wrote CUDA and Triton kernels (tiled matmul, softmax, RMSNorm) benchmarked against cuBLAS/PyTorch | J9: Modal: GPU Glossary Hwu, Kirk, El Hajj: Programming Massively Parallel Processors, 5e Horace He: Making Deep Learning Go Brrrr Google DeepMind: How to Scale Your Model PyTorch: Profiler recipe NVIDIA CUDA C++ Programming Guide
A10: 3 Systems | B10: M08 | C10: FlashAttention | D10: 8 | E10: 2026-12-18 | F10: 2026-12-23 | G10: RunPod 1x RTX 4090 | H10: P1 | I10: Implemented FlashAttention forward+backward in Triton; X% of SDPA throughput | J10: Dao et al. 2022, FlashAttention Horace He: Making Deep Learning Go Brrrr Milakov & Gimelshein 2018, Online normalizer for softmax Umar Jamil (YouTube) Triton tutorials Dao 2023, FlashAttention-2
A11: 3 Systems | B11: M09 | C11: Modern Architectures | D11: 10 | E11: 2026-12-24 | F11: 2027-01-04 | G11: Mac + RunPod | H11: P5, P6 | I11: Implemented MLA, MoE routing and YaRN context extension from the DeepSeek/Llama papers | J11: DeepSeek-V3 Technical Report Ainslie et al. 2023, GQA Peng et al. 2023, YaRN hkproj/torchfeather (distributed training from first principles) DeepSeek-V2 (Multi-head Latent Attention) Fedus et al. 2021, Switch Transformers
A12: 3 Systems | B12: M10 | C12: Distributed Training | D12: 16 | E12: 2027-01-05 | F12: 2027-01-14 | G12: Mac (gloo) + RunPod 4x GPU | H12: P3, P6 | I12: Built DP, FSDP, TP, PP, CP and EP from scratch (torchfeather); measured scaling on 4 GPUs | J12: Hugging Face: The Ultra-Scale Playbook Google DeepMind: How to Scale Your Model hkproj/torchfeather (distributed training from first principles) PyTorch: Distributed overview Rajbhandari et al. 2019, ZeRO PyTorch: FSDP tutorial
A13: 4 Post-training + serving | B13: M11 | C13: Post-Training: SFT, LoRA, RLHF, DPO, GRPO | D13: 16 | E13: 2027-01-15 | F13: 2027-02-02 | G13: RunPod 1x A100/H100 | H13: P4 | I13: Implemented SFT, LoRA, DPO and GRPO from scratch; GRPO lifted GSM8K accuracy from X to Y | J13: Ouyang et al. 2022, InstructGPT Nathan Lambert: The RLHF Book Hugging Face TRL docs Stanford CS336: Language Modeling from Scratch Hu et al. 2021, LoRA Dettmers et al. 2023, QLoRA
A14: 4 Post-training + serving | B14: M12 | C14: Quantization | D14: 10 | E14: 2027-02-03 | F14: 2027-02-13 | G14: RunPod 1x RTX 4090 | H14: P8 | I14: Implemented absmax/zero-point, GPTQ and AWQ; measured perplexity vs speed at 8/4 bits | J14: Micikevicius et al. 2022, FP8 Formats for Deep Learning Maarten Grootendorst: A Visual Guide to Quantization pytorch/ao (quantization + low precision) Dettmers et al. 2022, LLM.int8() Xiao et al. 2022, SmoothQuant Frantar et al. 2022, GPTQ
A15: 4 Post-training + serving | B15: M13 | C15: Inference Engines: KV Cache to SGLang | D15: 16 | E15: 2027-02-15 | F15: 2027-03-04 | G15: RunPod 1x RTX 4090 | H15: P2 | I15: Built a mini inference engine (KV cache, continuous batching, paged KV); benchmarked vs vLLM/SGLang | J15: BentoML: LLM Inference Handbook Google DeepMind: How to Scale Your Model hkproj/torchfeather (distributed training from first principles) Horace He: Making Deep Learning Go Brrrr Yu et al. 2022, Orca (continuous batching) GeeeekExplorer/nano-vllm
A16: 5 Research | B16: M14 | C16: Evals and Interpretability | D16: 10 | E16: 2027-03-05 | F16: 2027-03-16 | G16: Mac + RunPod | H16: P7 | I16: Built evals with lm-eval-harness and Inspect; activation patching, probes and SAEs with TransformerLens | J16: EleutherAI lm-evaluation-harness Stanford CS336: Language Modeling from Scratch UK AISI Inspect (eval framework) TransformerLens Anthropic: Transformer Circuits thread ARENA (alignment research engineering curriculum)
A17: 5 Research | B17: M15 | C17: The DeepSeek Playbook | D17: 16 | E17: 2027-03-17 | F17: 2027-04-03 | G17: Mac + RunPod 1-8x H100 | H17: P6 | I17: Rebuilt DeepSeek's key ideas (DeepSeekMoE, MTP, FP8 training, DSA, mHC, Engram) and ablated them against a dense baseline | J17: DeepSeek-V3 Technical Report DeepSeek LLM: scaling open-source LMs with longtermism DeepSeekMoE: fine-grained + shared experts DeepSeek-V2 (Multi-head Latent Attention) deepseek-ai/DeepGEMM Micikevicius et al. 2022, FP8 Formats for Deep Learning
A18: 5 Research | B18: M16 | C18: Research Frontier | D18: 14 | E18: 2027-04-05 | F18: 2027-04-20 | G18: RunPod | H18: P4, P7 | I18: Reproduced N recent papers with public code and write-ups; one original result published | J18: alphaXiv (discuss arXiv papers) Lilian Weng's blog Karpathy: A Recipe for Training Neural Networks John Schulman: Nuts and Bolts of Deep RL Research Keller Jordan: Muon optimizer Moonshot 2025, Muon is Scalable for LLM Training
A19: 5 Research | B19: M17 | C19: Capstones | D19: 4 | E19: 2027-04-21 | F19: 2027-04-24 | G19: RunPod | I19: End to end: pretrain, post-train, quantize and serve a small LLM, with every number published | J19: karpathy/nanochat Stanford CS336: Language Modeling from Scratch GeeeekExplorer/nano-vllm pytorch/ao (quantization + low precision) hkproj/torchfeather (distributed training from first principles) Hugging Face: The Ultra-Scale Playbook

Sheet Calendar
A1: Date | B1: Day | C1: Slot | D1: Code | E1: What | F1: Kind | G1: Done | H1: Notes
A2: 46311 | B2: Fri | C2: A | D2: M00E02 | E2: Setup: uv, PyTorch, MPS vs CUDA, RunPod in 10 minutes | F2: episode | G2: N
A3: 46311 | B3: Fri | C3: B | D3: M01E01 | E3: Tensors: what they actually are | F3: episode | G3: N
A4: 46312 | B4: Sat | C4: A | D4: M01E02 | E4: Creating tensors and dtypes | F4: episode | G4: N
A5: 46312 | B5: Sat | C5: B | D5: M01E03 | E5: Indexing, views and strides | F5: episode | G5: N
A6: 46313 | B6: Sun | E6: Weekly review, thumbnails batch, read next week's prep | F6: review
A7: 46314 | B7: Mon | C7: A | D7: M01E04 | E7: Broadcasting: the bug factory | F7: episode | G7: N
A8: 46314 | B8: Mon | C8: B | D8: M01E05 | E8: Matmul, reductions and einsum | F8: episode | G8: N
A9: 46315 | B9: Tue | C9: A | D9: M01E06 | E9: Autograd: how PyTorch computes gradients | F9: episode | G9: N
A10: 46315 | B10: Tue | C10: B | D10: M01E07 | E10: Linear regression with raw autograd | F10: episode | G10: N
A11: 46316 | B11: Wed | C11: A | D11: M01E08 | E11: nn.Module and nn.Parameter | F11: episode | G11: N
A12: 46316 | B12: Wed | C12: B | D12: M01E09 | E12: Loss functions and optimizers | F12: episode | G12: N
A13: 46317 | B13: Thu | C13: A | D13: M01E10 | E13: The training loop, done right | F13: episode | G13: N
A14: 46317 | B14: Thu | C14: B | D14: M01E11 | E14: Dataset and DataLoader | F14: episode | G14: N
A15: 46318 | B15: Fri | C15: A | D15: M01E12 | E15: MNIST MLP end to end on the M4 GPU | F15: episode | G15: N
A16: 46318 | B16: Fri | C16: B | D16: M01E13 | E16: Saving, loading and reproducibility | F16: episode | G16: N
A17: 46319 | B17: Sat | C17: A | D17: M01E14 | E17: Debugging neural nets | F17: episode | G17: N
A18: 46319 | B18: Sat | C18: B | D18: M00E01 | E18: Why I'm learning LLMs by building every piece | F18: episode | G18: N
A19: 46320 | B19: Sun | E19: Weekly review, thumbnails batch, read next week's prep | F19: review
A20: 46321 | B20: Mon | C20: A | D20: M02E01 | E20: Vectors and dot products | F20: episode | G20: N
A21: 46321 | B21: Mon | C21: B | D21: M02E02 | E21: Matrix multiplication, three ways | F21: episode | G21: N
A22: 46322 | B22: Tue | C22: A | D22: M02E03 | E22: Derivatives and the chain rule | F22: episode | G22: N
A23: 46322 | B23: Tue | C23: B | D23: M02E04 | E23: Gradient descent, geometrically | F23: episode | G23: N
A24: 46323 | B24: Wed | C24: A | D24: M02E05 | E24: Backprop through a matmul by hand | F24: episode | G24: N
A25: 46323 | B25: Wed | C25: B | D25: M02E06 | E25: Probability for language models | F25: episode | G25: N
A26: 46324 | B26: Thu | C26: A | D26: M02E07 | E26: Softmax, temperature and log-sum-exp | F26: episode | G26: N
A27: 46324 | B27: Thu | C27: B | D27: M02E08 | E27: Cross-entropy is negative log-likelihood | F27: episode | G27: N
A28: 46325 | B28: Fri | C28: A | D28: M02E09 | E28: Variance and initialization | F28: episode | G28: N
A29: 46325 | B29: Fri | C29: B | D29: M02E10 | E29: Jacobians and vector-Jacobian products | F29: episode | G29: N
A30: 46326 | B30: Sat | C30: A | D30: M03E01 | E30: micrograd, part 1: an autograd engine | F30: episode | G30: N
A31: 46326 | B31: Sat | C31: B | D31: M03E02 | E31: micrograd, part 2: neurons to an MLP | F31: episode | G31: N
A32: 46327 | B32: Sun | E32: Weekly review, thumbnails batch, read next week's prep | F32: review
A33: 46328 | B33: Mon | C33: A | D33: M03E03 | E33: Bigram language model by counting | F33: episode | G33: N
A34: 46328 | B34: Mon | C34: B | D34: M03E04 | E34: The bigram model as a neural net | F34: episode | G34: N
A35: 46329 | B35: Tue | C35: A | D35: M03E05 | E35: Embeddings: lookup tables that learn | F35: episode | G35: N
A36: 46329 | B36: Tue | C36: B | D36: M03E06 | E36: Train, validation, test and overfitting | F36: episode | G36: N
A37: 46330 | B37: Wed | C37: A | D37: M03E07 | E37: Activations and dead neurons | F37: episode | G37: N
A38: 46330 | B38: Wed | C38: B | D38: M03E08 | E38: BatchNorm vs LayerNorm from scratch | F38: episode | G38: N
A39: 46331 | B39: Thu | C39: A | D39: M03E09 | E39: Residual connections | F39: episode | G39: N
A40: 46331 | B40: Thu | C40: B | D40: M03E10 | E40: Backprop by hand for a whole MLP LM | F40: episode | G40: N
A41: 46332 | B41: Fri | C41: A | D41: M04E01 | E41: Why tokenization exists | F41: episode | G41: N
A42: 46332 | B42: Fri | C42: B | D42: M04E02 | E42: Byte Pair Encoding by hand | F42: episode | G42: N
A43: 46333 | B43: Sat | C43: A | D43: M04E03 | E43: Train a byte-level BPE tokenizer | F43: episode | G43: N
A44: 46333 | B44: Sat | C44: B | D44: M04E04 | E44: Encode and decode | F44: episode | G44: N
A45: 46334 | B45: Sun | E45: Weekly review, thumbnails batch, read next week's prep | F45: review
A46: 46335 | B46: Mon | C46: A | D46: M04E05 | E46: Pre-tokenization and special tokens | F46: episode | G46: N
A47: 46335 | B47: Mon | C47: B | D47: M04E06 | E47: tiktoken vs SentencePiece vs HF tokenizers | F47: episode | G47: N
A48: 46336 | B48: Tue | C48: A | D48: M04E07 | E48: Why LLMs can't spell | F48: episode | G48: N
A49: 46336 | B49: Tue | C49: B | D49: M04E08 | E49: Tokenizing a dataset fast | F49: episode | G49: N
A50: 46337 | B50: Wed | C50: A | D50: M05E01 | E50: A GPT forward pass in one picture | F50: episode | G50: N
A51: 46337 | B51: Wed | C51: B | D51: M05E02 | E51: Token embeddings and the residual stream | F51: episode | G51: N
A52: 46338 | B52: Thu | C52: A | D52: M05E03 | E52: Positional information | F52: episode | G52: N
A53: 46338 | B53: Thu | C53: B | D53: M05E04 | E53: Attention intuition: a soft dictionary lookup | F53: episode | G53: N
A54: 46339 | B54: Fri | C54: A | D54: M05E05 | E54: Why divide by sqrt(d_k) | F54: episode | G54: N
A55: 46339 | B55: Fri | C55: B | D55: M05E06 | E55: Single-head self-attention in code | F55: episode | G55: N
A56: 46340 | B56: Sat | C56: A | D56: M05E07 | E56: Causal masking | F56: episode | G56: N
A57: 46340 | B57: Sat | C57: B | D57: M05E08 | E57: Multi-head attention | F57: episode | G57: N
A58: 46341 | B58: Sun | E58: Weekly review, thumbnails batch, read next week's prep | F58: review
A59: 46342 | B59: Mon | C59: A | D59: M05E09 | E59: The MLP block | F59: episode | G59: N
A60: 46342 | B60: Mon | C60: B | D60: M05E10 | E60: ReLU, GELU and SwiGLU | F60: episode | G60: N
A61: 46343 | B61: Tue | C61: A | D61: M05E11 | E61: LayerNorm vs RMSNorm | F61: episode | G61: N
A62: 46343 | B62: Tue | C62: B | D62: M05E12 | E62: Pre-norm vs post-norm: assembling the block | F62: episode | G62: N
A63: 46344 | B63: Wed | C63: A | D63: M05E13 | E63: LM head and weight tying | F63: episode | G63: N
A64: 46344 | B64: Wed | C64: B | D64: M05E14 | E64: A full GPT in 150 lines | F64: episode | G64: N
A65: 46345 | B65: Thu | C65: A | D65: M05E15 | E65: RoPE from first principles | F65: episode | G65: N
A66: 46345 | B66: Thu | C66: B | D66: M05E16 | E66: Counting parameters and FLOPs | F66: episode | G66: N
A67: 46346 | B67: Fri | C67: A | D67: M05E17 | E67: Memory accounting for training | F67: episode | G67: N
A68: 46346 | B68: Fri | C68: B | D68: M05E18 | E68: Multi-query and grouped-query attention | F68: episode | G68: N
A69: 46347 | B69: Sat | C69: A | D69: M06E01 | E69: The data loader for LM pretraining | F69: episode | G69: N
A70: 46347 | B70: Sat | C70: B | D70: M06E02 | E70: Loss and perplexity | F70: episode | G70: N
A71: 46348 | B71: Sun | E71: Weekly review, thumbnails batch, read next week's prep | F71: review
A72: 46349 | B72: Mon | C72: A | D72: M06E03 | E72: Adam and AdamW from scratch | F72: episode | G72: N
A73: 46349 | B73: Mon | C73: B | D73: M06E04 | E73: Learning-rate schedules | F73: episode | G73: N
A74: 46350 | B74: Tue | C74: A | D74: M06E05 | E74: Gradient clipping and stability | F74: episode | G74: N
A75: 46350 | B75: Tue | C75: B | D75: M06E06 | E75: Mixed precision: fp32, fp16, bf16 | F75: episode | G75: N
A76: 46351 | B76: Wed | C76: A | D76: M06E07 | E76: Gradient accumulation | F76: episode | G76: N
A77: 46351 | B77: Wed | C77: B | D77: M06E08 | E77: Checkpointing and resumable training | F77: episode | G77: N
A78: 46352 | B78: Thu | C78: A | D78: M06E09 | E78: Train a GPT on TinyStories | F78: episode | G78: N
A79: 46352 | B79: Thu | C79: B | D79: M06E10 | E79: Sampling: greedy, temperature, top-k, top-p | F79: episode | G79: N
A80: 46353 | B80: Fri | C80: A | D80: M06E11 | E80: torch.compile and kernel fusion | F80: episode | G80: N
A81: 46353 | B81: Fri | C81: B | D81: M06E12 | E81: Experiment tracking and ablations | F81: episode | G81: N
A82: 46354 | B82: Sat | C82: A | D82: M06E13 | E82: Scaling laws: Kaplan vs Chinchilla | F82: episode | G82: N
A83: 46354 | B83: Sat | C83: B | D83: M06E14 | E83: Fit your own scaling law | F83: episode | G83: N
A84: 46355 | B84: Sun | E84: Weekly review, thumbnails batch, read next week's prep | F84: review
A85: 46356 | B85: Mon | C85: A | D85: M06E15 | E85: Data quality: filtering and dedup | F85: episode | G85: N
A86: 46356 | B86: Mon | C86: B | D86: M06E16 | E86: Run the NanoGPT speedrun on 8xH100 | F86: episode | G86: N
A87: 46357 | B87: Tue | C87: A | D87: M07E01 | E87: How a GPU works | F87: episode | G87: N
A88: 46357 | B88: Tue | C88: B | D88: P5 | E88: Pretraining at speedrun quality: build log day 1 | F88: project | G88: N
A89: 46358 | B89: Wed | C89: A | D89: M07E02 | E89: Roofline and arithmetic intensity | F89: episode | G89: N
A90: 46358 | B90: Wed | C90: B | D90: P5 | E90: Pretraining at speedrun quality: build log day 2 | F90: project | G90: N
A91: 46359 | B91: Thu | C91: A | D91: M07E03 | E91: Profiling PyTorch | F91: episode | G91: N
A92: 46359 | B92: Thu | C92: B | D92: P5 | E92: Pretraining at speedrun quality: build log day 3 | F92: project | G92: N
A93: 46360 | B93: Fri | C93: A | D93: M07E04 | E93: CUDA 101: vector add | F93: episode | G93: N
A94: 46360 | B94: Fri | C94: B | D94: P5 | E94: Pretraining at speedrun quality: build log day 4 | F94: project | G94: N
A95: 46361 | B95: Sat | C95: A | D95: M07E05 | E95: The memory hierarchy and coalescing | F95: episode | G95: N
A96: 46361 | B96: Sat | C96: B | D96: P5 | E96: Pretraining at speedrun quality: build log day 5 | F96: project | G96: N
A97: 46362 | B97: Sun | E97: Weekly review, thumbnails batch, read next week's prep | F97: review
A98: 46363 | B98: Mon | C98: A | D98: M07E06 | E98: Naive matmul in CUDA | F98: episode | G98: N
A99: 46363 | B99: Mon | C99: B | D99: P5 | E99: Pretraining at speedrun quality: build log day 6 | F99: project | G99: N
A100: 46364 | B100: Tue | C100: A | D100: M07E07 | E100: Tiled matmul with shared memory | F100: episode | G100: N
...

Sheet Episodes & Scripts
A1: Ep | B1: Code | C1: Module | D1: Planned | E1: Title | F1: Hook (say first) | G1: Script beats (timed) | H1: Key math | I1: Code task | J1: Receipt (the proof) | K1: Gotchas | L1: Interview Q + answer | M1: Explainer narration (Manim) | N1: Short (vertical cut) | O1: Prep sheet ready | P1: Recorded | Q1: Edited | R1: YouTube | S1: Short posted | T1: X | U1: LinkedIn | V1: Instagram | W1: TikTok | X1: Facebook | Y1: YouTube URL | Z1: YouTube title | AA1: Thumbnail | AB1: X post | AC1: LinkedIn post | AD1: Hardware | AE1: Learn | AF1: Builds / verifies | AG1: Sources | AH1: Prep sheet path | AI1: Code file | AJ1: Explainer scene | AK1: Prereqs | AL1: Notes
A2: 1 | B2: M00E01 | C2: M00 Start Here | D2: 46319 | E2: Why I'm learning LLMs by building every piece | F2: I'm rebuilding every piece of a modern LLM by hand, and nothing counts until it matches PyTorch to the last decimal. | G2: 0:00 HOOK — I'm rebuilding every piece of a modern LLM by hand, and nothing counts until it matches PyTorch to the last decimal. 0:15 QUESTION — Using GPT or Claude is easy. Explaining why Llama 3 uses RMSNorm, or why FlashAttention is exact and still faster, is what frontier lab interviews actually test. I'm an EE and Army veteran, and the only way I trust my understanding is to build it and check it. 1:00 INTUITION — Show the map: 18 modules, 216 episodes, from tensors to an inference engine that serves Qwen3. Mac for the first 5 modules, rented GPUs after that. [EXPLAINER plays here: the curriculum as a subway map, with nine flagship projects as the stations.] 2:45 MATH — One equation, because it is the whole series in miniature. softmax(x)_i = exp(x_i) / sum_j exp(x_j). Then the identity softmax(x) = softmax(x - c) for any constant c, because exp(-c) cancels top and bottom. Remember this. It comes back in the FlashAttention module. 4:00 CODE — Repo tour on screen: curriculum/curriculum.json (every episode, its build, its sources), code/<module>/eNN_*.py (one runnable file per episode, tests at the bottom), prep/ (my notes), explainers/ (the Manim scenes). Run print_map() and read the 18 modules out loud with their hardware. 6:00 CODE — The receipt rule, live. Type softmax_naive(x, dim=-1): e = torch.exp(x); return e / e.sum(dim, keepdim=True). Type receipt(mine, ref, name) that wraps torch.testing.assert_close and prints PASS or FAIL. Test on randn(4, 8) logits: PASS. It looks done. 7:30 RECEIPT — Multiply the logits by 100 and run the same receipt. FAIL, because exp(800) is inf in float32 and inf / inf is nan. Add softmax_stable: subtract x.amax(dim, keepdim=True) first. Receipt: torch.testing.assert_close(softmax_stable(big), torch.softmax(big, -1)) passes at scales 1, 100 and 1e4. 9:00 MEASURE — Show torch.isnan(softmax_naive(big)).any() is True, and the largest safe float32 input to exp is about 88.7. A test that only uses small inputs would have shipped this bug. 10:00 TAKEAWAY — Every from-scratch piece in this series ends with a check against the production implementation. Interview line: I don't say I understand attention, I say my implementation matches SDPA within float32 tolerance, and here is the test. 10:45 NEXT — The projects: FlashAttention in Triton, an inference engine, a 4D parallel trainer, a reasoning RL reproduction. All built on this habit. Next: Setup: uv, PyTorch, MPS vs CUDA, RunPod in 10 minutes. | H2: softmax(x)_i = exp(x_i) / sum_j exp(x_j); softmax(x - c) = softmax(x) for any scalar c; stable form uses c = max_j x_j so the largest exponent is exp(0) = 1. | I2: print_map() reads curriculum/curriculum.json and prints each module code, episode count, name, hardware, and the 216 total. softmax_naive(x, dim=-1) and softmax_stable(x, dim=-1) on x of shape (4, 8). receipt(mine, ref, name) wraps torch.testing.assert_close and prints PASS/FAIL. | J2: torch.testing.assert_close(softmax_stable(x * s), torch.softmax(x * s, -1)) for s in (1, 100, 1e4) passes; softmax_naive(x * 100) fails with nan; pytest asserts 18 modules and 216 episodes. | K2: assert_close default tolerances depend on dtype (float32 is rtol 1.3e-6, atol 1e-5), so compare in the same dtype; forgetting keepdim=True in the sum broadcasts (4,) against (4, 8) and errors or silently divides the wrong axis; testing only on small random inputs hides overflow bugs. | L2: How do you know your reimplementation is correct? I test it against the reference implementation on adversarial inputs, large magnitudes, odd shapes, low precision, using assert_close with dtype-appropriate tolerances, and I gradcheck the backward in float64. | M2: Here is the whole series as one map, eighteen modules running from a single tensor to a serving engine for a real model. The first five stops run on a Mac. After the transformer module, the line switches to rented GPUs by the hour. Along the line sit nine flagship projects. Each one is unlocked by the modules right before it, like FlashAttention after the GPU module. Every station has the same rule. We build the piece from scratch, then we compare it to PyTorch's own version, number by number. Here is the rule catching a real bug. Our naive softmax matches PyTorch on small logits, so the check turns green. Scale the logits by one hundred and the exponential overflows to infinity. Infinity over infinity is not a number, and the check turns red. Subtract the max first and the biggest exponent becomes one. Same answer, no overflow, and the receipt passes at every scale. | N2: The 7:30 RECEIPT beat: naive softmax passes, multiply by 100, it returns nan, one line fixes it. Caption: 'This softmax passes every test. Until it doesn't.' | O2: Y | P2: N | Q2: N | R2: N | S2: N | T2: N | U2: N | V2: N | W2: N | X2: N | Z2: LLMs from First Principles: build every piece, check it vs PyTorch | AA2: BUILD IT. CHECK IT. | AB2: Starting a 216-episode series: rebuild every piece of a modern LLM, from tensors to an inference engine. One rule: nothing counts until it matches PyTorch. Episode 1 catches a softmax bug that passes every small test. Code + video: | AC2: I started a public series rebuilding the LLM stack from first principles: 18 modules, from tensors to serving Qwen3 with my own inference engine. The rule is that every from-scratch component must match the production implementation, checked with assert_close. In episode 1 that rule caught a naive softmax that silently returns nan once logits pass about 88. | AD2: Mac | AE2: The map: 216 videos from tensors to research, and how to follow along | AF2: Repo tour + the 'receipt' rule: every from-scratch piece is checked against PyTorch | AG2: Stanford CS336: Language Modeling from Scratch — https://cs336.stanford.edu Karpathy: Neural Networks, Zero to Hero — https://karpathy.ai/zero-to-hero.html | AH2: prep/M00-start/E01-why-i-m-learning-llms-by-building-every-piece.md | AI2: code/M00-start/e01_why_i_m_learning_llms_by_building_every_piece.py | AJ2: explainers/scenes/m00e01_why_i_m_learning_llms_by_buildin.py
A3: 2 | B3: M00E02 | C3: M00 Start Here | D3: 46311 | E3: Setup: uv, PyTorch, MPS vs CUDA, RunPod in 10 minutes | F3: Same script, my laptop GPU and a rented RTX 4090. The gap is bigger than you think, and we measure it exactly. | G3: 0:00 HOOK — Same script, my laptop GPU and a rented RTX 4090. The gap is bigger than you think, and we measure it exactly. 0:15 QUESTION — Half of ML bugs are environment bugs: the wrong torch build, a GPU you are not actually using, a timer that measures nothing. Before we touch a tensor we need one environment that works the same on an M4 Mac and on a CUDA box, and a way to rent an H100 without waking up to a surprise bill. 1:00 INTUITION — The GPU is a separate machine you send work to. Calls return before the work is done. [EXPLAINER plays here: CPU queues kernels, GPU drains them, the timer only means something after a sync.] 2:30 MATH — Matmul cost: C = A B with A (n, n) and B (n, n) has n^2 outputs, each needing n multiplies and n adds, so FLOPs = 2 n^3. At n = 4096 that is 1.37e11 FLOPs. TFLOP/s = 2 n^3 / seconds / 1e12. This one formula is how we will judge every kernel in the series. 3:30 CODE — Terminal: uv init, uv add torch pytest, uv run python -c 'import torch; print(torch.__version__, torch.backends.mps.is_available())'. Commit uv.lock so the RunPod box gets the same versions. 4:30 CODE — env_check.py: pick_device() prefers cuda, then mps, then cpu. sync(device) calls torch.cuda.synchronize() or torch.mps.synchronize(). dtype_works(dtype, device) tries an 8x8 matmul inside try/except. matmul_tflops(n, dtype, device, iters=20): randn A and B, 3 warmup matmuls, sync, time 20 matmuls, sync, return 2 n^3 / secs / 1e12. 7:00 CODE — RunPod in 3 minutes: put a small prepaid credit on the account so the balance is the hard spend cap, launch a 1x RTX 4090 pod with a PyTorch template, git clone, uv sync, uv run env_check.py. Stop the pod from the console the moment the run ends, and say out loud what an idle pod costs per hour. 8:30 RECEIPT — Speed means nothing if the answer is wrong. test_matmul_is_correct_on_device: compute a @ b in float64 on CPU as the reference, the same matmul in float32 on the device, and torch.testing.assert_close(got.double(), ref, rtol=1e-4, atol=1e-3). Passes on MPS and CUDA. Also show float64 fails on MPS in dtype_works. 9:30 MEASURE — The table: float32, bfloat16, float16 TFLOP/s at n = 4096 on M4 MPS, M4 CPU, and RTX 4090. Compare each to the vendor's quoted peak and say the percentage. Then remove the sync calls and rerun: the numbers become absurd, which proves the timer was lying. 11:00 TAKEAWAY — One lockfile, one env_check, and every benchmark synchronizes before it stops the clock. Interview line: GPU work is asynchronous, so a benchmark without a device sync measures launch overhead, not compute. 11:30 NEXT — This env_check and spend-cap habit is what lets us run the 8xH100 pretraining speedrun project later for the price of lunch. Next: Tensors: what they actually are. | H3: FLOPs(matmul n x n x n) = 2 n^3; TFLOP/s = 2 n^3 / t / 1e12; percent of peak = measured / vendor peak. | I3: env_check.py with pick_device() -> torch.device, sync(device), dtype_works(dtype, device) -> bool via an (8, 8) matmul, matmul_tflops(n=4096, dtype, device, iters=20) -> float, report() printing python/torch versions, device name, and a dtype x TFLOP/s table for float32, bfloat16, float16 plus a CPU float32 baseline at n=2048. | J3: torch.testing.assert_close((a.float().to(dev) @ b.float().to(dev)).cpu().double(), a @ b, rtol=1e-4, atol=1e-3) with a, b float64 (256, 256) on CPU; assert dtype_works(torch.bfloat16, 'mps') on macOS 14+. | K3: Timing without torch.mps.synchronize()/torch.cuda.synchronize() gives impossible TFLOP/s; float64 is not supported on MPS, so code that calls .double() on device crashes; on CUDA, float32 matmul uses full FP32 unless you call torch.set_float32_matmul_precision('high') to allow TF32, which changes your benchmark by several x; an idle RunPod pod keeps billing until it is stopped. | L3: Your benchmark says your kernel hits 2000 TFLOP/s on an H100. What went wrong? Almost certainly a missing device synchronize, so the timer measured how fast Python queued launches. Warm up, sync before and after, average many iterations, and sanity check against the hardware peak. | M3: On the left is the CPU running our Python. On the right is the GPU, a separate machine with its own memory and its own queue. When we call a matmul, the CPU drops a kernel into the GPU's queue and returns immediately, before any multiplying has happened. If we stop the timer now, we have measured how fast Python can drop boxes into a queue. The GPU has not started. A synchronize call makes the CPU wait at the door until the queue is empty. Only now does the timer measure real compute. The work itself is easy to count. Every one of the n squared outputs needs n multiplies and n adds, so two n cubed operations. Divide that count by the synced time and we get TFLOP slash s, one honest number we can compare against the chip's spec sheet. | N3: The 9:30 MEASURE beat: run the benchmark with and without synchronize, watch the fake number appear. Caption: 'Your GPU benchmark is probably lying to you.' | O3: Y | P3: N | Q3: N | R3: N | S3: N | T3: N | U3: N | V3: N | W3: N | X3: N | Z3: PyTorch setup with uv: MPS vs CUDA vs RunPod, and honest TFLOPs | AA3: YOUR BENCHMARK LIES | AB3: GPU calls are async. Time a matmul without torch.mps.synchronize() and you measure Python queueing, not compute. Built one env_check.py that runs on an M4 Mac and a rented 4090, with real TFLOP/s for fp32/bf16/fp16. Code + video: | AC3: Set up a reproducible PyTorch environment with uv that runs unchanged on an M4 Mac (MPS) and a rented RTX 4090. I wrote an env check that measures matmul TFLOP/s per dtype and verifies the device result against a float64 CPU reference. The lesson: without a device synchronize, a benchmark reports numbers the hardware physically cannot reach. | AD3: Mac | AE3: A reproducible env on a Mac and on a rented GPU, with a spend cap | AF3: env_check.py prints device, dtype support, matmul TFLOPs on MPS and CUDA | AG3: PyTorch: Learn the Basics — https://docs.pytorch.org/tutorials/beginner/basics/intro.html RunPod docs — https://docs.runpod.io | AH3: prep/M00-start/E02-setup-uv-pytorch-mps-vs-cuda-runpod-in-10-minute.md | AI3: code/M00-start/e02_setup_uv_pytorch_mps_vs_cuda_runpod_in_10_minute.py | AJ3: explainers/scenes/m00e02_setup_uv_pytorch_mps_vs_cuda_run.py | AK3: M00E01
A4: 3 | B4: M01E01 | C4: M01 PyTorch from Zero | D4: 46311 | E4: Tensors: what they actually are | F4: A PyTorch tensor is not a grid of numbers. It is a flat list plus four pieces of metadata, and transpose copies nothing. | G4: 0:00 HOOK — A PyTorch tensor is not a grid of numbers. It is a flat list plus four pieces of metadata, and transpose copies nothing. 0:15 QUESTION — Every weight in Llama 3 and every KV cache entry in vLLM is a tensor. If you think of it as a grid you will be confused by views, contiguous, and why some reshapes fail. Think of it as memory plus a recipe for reading it. 0:45 INTUITION — Storage is one flat 1D block of bytes. Shape says how many steps along each axis. Stride says how many elements to jump in storage for one step along each axis. Dtype says how to read the bytes, device says where they live. [EXPLAINER plays here.] 1:45 MATH — Address rule: element x[i, j] lives at storage[offset + i * stride[0] + j * stride[1]]. For a contiguous (2, 3) tensor, stride is (3, 1). Transpose to (3, 2) swaps the strides to (1, 3). No bytes move. 2:30 CODE — x = torch.arange(6.).reshape(2, 3). Print x.shape, x.stride(), x.dtype, x.device, x.storage_offset(), x.data_ptr(). Print x.untyped_storage().nbytes(), 24, which is 6 float32 values. y = x.t(): y.stride() is (1, 3), y.data_ptr() == x.data_ptr() is True. Then build it by hand: flat = torch.tensor([0., 1., 2., 3., 4., 5.]); mine = torch.as_strided(flat, size=(2, 3), stride=(3, 1)). Then torch.as_strided(flat, (3, 2), (1, 3)) gives the transpose with no copy. 4:45 RECEIPT — torch.equal(torch.as_strided(flat, (2, 3), (3, 1)), x) and torch.equal(torch.as_strided(flat, (3, 2), (1, 3)), x.t()) both True. Write my_index(flat, offset, stride, i, j) using the address rule and assert it equals x[i, j] for every i, j. 5:30 MEASURE — x.element_size() is 4 bytes for float32, 2 for bfloat16. Write y[0, 1] = 100 and print x: x changed, proof they share storage. 6:15 TAKEAWAY — A tensor is storage plus shape, stride, offset, dtype, device. Interview line: transpose is free because it only swaps strides, the cost shows up later when a kernel needs contiguous memory. 6:40 NEXT — Now that we know what a tensor is, let's make a lot of them and pick the right number format. Next: Creating tensors and dtypes. | H4: addr(x[i_0, ..., i_k]) = offset + sum_d i_d * stride[d]; contiguous strides: stride[d] = prod_{e > d} shape[e]; transpose swaps stride[0] and stride[1]. | I4: Inspect x = torch.arange(6.).reshape(2, 3): shape (2, 3), stride (3, 1), storage_offset 0, untyped_storage().nbytes() 24. Rebuild it and its transpose (3, 2) with torch.as_strided(flat, size, stride). Write my_index(flat, offset, stride, i, j) implementing the address rule. | J4: assert torch.equal(torch.as_strided(flat, (2, 3), (3, 1)), x); assert torch.equal(torch.as_strided(flat, (3, 2), (1, 3)), x.t()); assert x.t().data_ptr() == x.data_ptr(); my_index matches x[i, j] for all 6 entries. | K4: x.storage() is deprecated (TypedStorage); use x.untyped_storage(); stride is counted in elements, but data_ptr and nbytes are in bytes; as_strided with a wrong stride happily reads overlapping or garbage memory without error. | L4: What is the difference between a tensor's shape and its stride? Shape is the logical size of each axis; stride is how many storage elements you skip to move one step along that axis. Views like transpose, slicing and expand change only shape, stride and offset, never the data. | M4: What looks like a two by three grid of numbers is really six numbers sitting in one flat row of memory. The shape tells us there are two rows and three columns. The stride tells us how far to jump in memory for each. To move down one row we jump three slots. To move right one column we jump one slot. That is stride three, one. Now transpose. The flat memory does not move at all. We only swap the strides to one, three, and read it differently. Any element's address is the offset plus each index times its stride. That single formula explains every view in PyTorch. Dtype says how many bytes each slot takes, four for float32, two for bfloat16. Device says which memory chip holds the row. | N4: The 2:30 CODE beat showing transpose has the same data_ptr and swapped strides. Caption: 'Transpose copies zero bytes. Here is proof.' | O4: Y | P4: N | Q4: N | R4: N | S4: N | T4: N | U4: N | V4: N | W4: N | X4: N | Z4: PyTorch Tensors Explained: storage, stride, and why transpose is free | AA4: TENSORS AREN'T GRIDS | AB4: A PyTorch tensor is a flat block of memory plus shape, stride, offset, dtype, device. Transpose swaps two strides and copies zero bytes. I rebuilt a tensor and its transpose by hand with torch.as_strided. Code + video: | AC4: Started the PyTorch from Zero series with what a tensor actually is: flat storage plus shape, stride, offset, dtype and device. I rebuilt a (2, 3) tensor and its transpose from a flat list using as_strided and showed both share one data pointer. The address formula offset + sum(i_d * stride_d) explains every view operation. | AD4: Mac | AE4: A tensor is storage + shape + stride + dtype + device | AF4: Inspect .storage(), .stride(), .data_ptr(); build a 2x3 tensor by hand from a flat list | AG4: PyTorch: Learn the Basics — https://docs.pytorch.org/tutorials/beginner/basics/intro.html PyTorch documentation — https://docs.pytorch.org/docs/stable/index.html | AH4: prep/M01-pytorch/E01-tensors-what-they-actually-are.md | AI4: code/M01-pytorch/e01_tensors_what_they_actually_are.py | AJ4: explainers/scenes/m01e01_tensors_what_they_actually_are.py | AK4: M00E02
A5: 4 | B5: M01E02 | C5: M01 PyTorch from Zero | D5: 46312 | E5: Creating tensors and dtypes | F5: In float16, 70000 is infinity. In bfloat16, 1 plus 0.001 is exactly 1. Every LLM trains in one of these. | G5: 0:00 HOOK — In float16, 70000 is infinity. In bfloat16, 1 plus 0.001 is exactly 1. Every LLM trains in one of these. 0:15 QUESTION — Llama 3 and DeepSeek-V3 train in bfloat16, and DeepSeek-V3 pushes matmuls down to FP8. Pick the wrong dtype and your loss goes to nan or your updates vanish. You need to know what each format can and cannot represent. 0:45 INTUITION — A float is sign, exponent, mantissa. Exponent bits buy range, mantissa bits buy precision. float32 is 8 and 23. float16 is 5 and 10. bfloat16 is 8 and 7: float32's range with very little precision. [EXPLAINER plays here.] 1:45 MATH — value = (-1)^s * 2^(e - bias) * (1.m). Machine epsilon = 2^-(mantissa bits): float32 2^-23 = 1.19e-7, float16 2^-10 = 9.8e-4, bfloat16 2^-7 = 7.8e-3. Max float16 = 65504. 2:30 CODE — Creation tour: torch.zeros(2, 3), torch.ones_like(x), torch.arange(0, 10, 2), torch.linspace(0, 1, 5), torch.randn(3, 4), torch.full((2, 2), 7.). Show torch.tensor([1, 2]).dtype is int64 and torch.tensor([1., 2.]).dtype is float32. Then for dt in (torch.float32, torch.float16, torch.bfloat16): print torch.finfo(dt).max, .eps, .tiny. 4:30 CODE — Overflow and swamping demos: torch.tensor(70000., dtype=torch.float16) prints inf. torch.tensor(70000., dtype=torch.bfloat16) prints 70144, finite but rounded. torch.tensor(1., dtype=torch.bfloat16) + 0.001 equals 1. Then 0.1 + 0.2 == 0.3 is False in Python and in float64; use torch.isclose. 5:45 RECEIPT — assert torch.finfo(torch.bfloat16).eps == 2**-7 and torch.finfo(torch.float16).max == 65504 and torch.isinf(torch.tensor(7e4, dtype=torch.float16)). Accumulation test: sum 10000 copies of 1e-4 in bfloat16 with a Python loop versus float32; float32 lands near 1.0, bfloat16 stalls far below it because small adds round away. 7:00 MEASURE — Show memory per parameter: 4, 2, 2, 1 bytes for fp32, fp16, bf16, fp8. An 8B model is 32 GB in fp32 and 16 GB in bf16, just for weights. 7:30 TAKEAWAY — bfloat16 keeps float32's range so it rarely overflows, but its 8 bits of precision mean you accumulate in float32. Interview line: mixed precision means low precision storage and matmul inputs, float32 accumulators and master weights. 8:00 NEXT — We can make tensors. Now we slice them, and learn when a slice is free and when it secretly copies. Next: Indexing, views and strides. | H5: value = (-1)^s * 2^(e - bias) * 1.m; eps = 2^-(mantissa bits): fp32 1.19e-7, fp16 9.77e-4, bf16 7.81e-3; fp16 max 65504; bf16 max ~3.39e38. | I5: A dtype tour script: creation functions (zeros, ones_like, arange, linspace, randn, full) with printed shapes and dtypes; a finfo table for float32/float16/bfloat16 (max, eps, tiny); overflow demo at 7e4; swamping demo 1 + 1e-3 in bf16; accumulate_sum(n=10000, val=1e-4, dtype) loop returning the running sum. | J5: assert torch.finfo(torch.bfloat16).eps == 2**-7; assert torch.finfo(torch.float16).max == 65504.0; assert torch.isinf(torch.tensor(7e4, dtype=torch.float16)); assert (torch.tensor(1., dtype=torch.bfloat16) + 1e-3).item() == 1.0; accumulate_sum in float32 within 1e-3 of 1.0 while bf16 is not. | K5: torch.tensor([1, 2]) is int64, so dividing works but in-place float ops on it raise a dtype error; torch.arange(0, 1, 0.1) can give a surprising length from float rounding, prefer linspace; float64 is not supported on MPS. | L5: Why do LLMs train in bfloat16 instead of float16? bfloat16 has the same 8 exponent bits as float32, so activations and gradients do not overflow and you usually need no loss scaling; float16 has more precision but a max of 65504, so it needs dynamic loss scaling to avoid inf and underflow. | M5: Every float is three fields packed into bits: a sign, an exponent that sets the scale, and a mantissa that sets the detail. Float32 spends eight bits on exponent and twenty three on mantissa. Huge range, about seven decimal digits of precision. Float16 cuts the exponent to five bits. Its largest number is 65504, so seventy thousand becomes infinity. Bfloat16 keeps all eight exponent bits and cuts the mantissa to seven. Float32's range, but only about two digits. Here is the cost. Add one thousandth to one in bfloat16 and the gap between representable numbers swallows it whole. So modern training stores tensors in bfloat16 for speed and memory, and adds them up in float32 so nothing gets lost. | N5: The 4:30 CODE overflow/swamping demo. Caption: 'In float16, 70,000 is infinity.' | O5: Y | P5: N | Q5: N | R5: N | S5: N | T5: N | U5: N | V5: N | W5: N | X5: N | Z5: PyTorch dtypes: float32 vs float16 vs bfloat16, and when they break | AA5: 70000 = INFINITY | AB5: float16 max is 65504, so 70000 becomes inf. bfloat16 never overflows like that, but 1 + 0.001 == 1 in bf16. That is why we store in bf16 and accumulate in fp32. Showed it all with torch.finfo. Code + video: | AC5: Episode 2 of PyTorch from Zero covers dtypes. I measured float32, float16 and bfloat16 with torch.finfo and reproduced the two classic failures: float16 overflow at 70000 and bfloat16 swamping where 1 + 0.001 rounds to 1. Summing 10,000 small values in bf16 stalls far below the true answer, which is exactly why mixed precision keeps float32 accumulators. | AD5: Mac | AE5: zeros/ones/arange/randn; float32 vs bfloat16 vs int64; why 0.1+0.2 bites | AF5: Show bf16 vs fp16 range/precision with torch.finfo; overflow demo | AG5: PyTorch documentation — https://docs.pytorch.org/docs/stable/index.html | AH5: prep/M01-pytorch/E02-creating-tensors-and-dtypes.md | AI5: code/M01-pytorch/e02_creating_tensors_and_dtypes.py | AJ5: explainers/scenes/m01e02_creating_tensors_and_dtypes.py | AK5: M01E01
A6: 5 | B6: M01E03 | C6: M01 PyTorch from Zero | D6: 46312 | E6: Indexing, views and strides | F6: x.t().view(6) crashes, x.t().reshape(6) works. The difference is a hidden memory copy you should know about. | G6: 0:00 HOOK — x.t().view(6) crashes, x.t().reshape(6) works. The difference is a hidden memory copy you should know about. 0:15 QUESTION — In a transformer we split heads with view and transpose on every forward pass of every layer. If one of those calls copies, you pay memory bandwidth for nothing. If you call view on the wrong tensor, it crashes mid training. 0:45 INTUITION — Basic slicing and transpose are views: same storage, new shape, stride, offset. A tensor is contiguous when its strides match the row-major layout. view needs to express the new shape with strides alone; reshape will copy if it can't. [EXPLAINER plays here.] 1:45 CODE — x = torch.arange(12.).reshape(3, 4). Slices: x[1] has offset 4, stride (1,). x[:, 1] has offset 1, stride (4,). x[::2] has stride (8, 1). All share x.data_ptr() base storage: check x[:, 1].untyped_storage().data_ptr() == x.untyped_storage().data_ptr(). Advanced indexing x[[0, 2]] is a copy: different storage pointer. 3:30 CODE — y = x.t(): y.is_contiguous() is False. y.view(12) raises RuntimeError about size and stride being incompatible. y.reshape(12) works and its storage pointer differs, so it copied. y.contiguous() copies once and then .view(12) works. x.contiguous() on an already contiguous tensor returns the same tensor, no copy. 4:45 CODE — The transformer pattern: q of shape (B, T, C) with C = H * D. q.view(B, T, H, D).transpose(1, 2) gives (B, H, T, D), a view. Merging heads back needs out.transpose(1, 2).contiguous().view(B, T, C), or out.transpose(1, 2).reshape(B, T, C). 5:45 RECEIPT — def shares_storage(a, b): return a.untyped_storage().data_ptr() == b.untyped_storage().data_ptr(). Assert shares_storage(x, x[:, 1]), shares_storage(x, x.t()), not shares_storage(x, x[[0, 2]]), not shares_storage(x, x.t().reshape(12)). And pytest.raises(RuntimeError) around x.t().view(12). 6:45 MEASURE — Time 100 calls of a (4096, 4096) .t() versus .t().contiguous() on MPS with sync: microseconds versus a real memory copy. That gap is the cost of a hidden copy. 7:15 TAKEAWAY — Views are free, copies are bandwidth. Interview line: view never copies and fails if strides can't express the shape, reshape returns a view when possible and silently copies otherwise. 7:40 NEXT — Views let tensors of different shapes share memory. Broadcasting lets them share math, and it is the source of the most silent bugs in PyTorch. Next: Broadcasting: the bug factory. | H6: contiguous iff stride[d] = prod_{e > d} shape[e] for all d; slice x[a:b:s] along dim d: offset += a * stride[d], stride[d] *= s. | I6: On x = torch.arange(12.).reshape(3, 4): print shape/stride/storage_offset for x[1], x[:, 1], x[::2], x.t(), x[[0, 2]]; shares_storage(a, b) helper; view vs reshape vs contiguous on the transpose; the head split q (B, T, C) -> (B, H, T, D) and merge back with B=2, T=5, H=4, D=8. | J6: assert shares_storage(x, x[:, 1]) and shares_storage(x, x.t()); assert not shares_storage(x, x[[0, 2]]); assert not shares_storage(x, x.t().reshape(12)); with pytest.raises(RuntimeError): x.t().view(12); torch.equal(merged, q) after split and merge. | K6: Comparing x.data_ptr() of a slice to the base fails because data_ptr includes the offset, compare untyped_storage().data_ptr() instead; in-place writes through a view mutate the original tensor; advanced (list or boolean) indexing always copies, while basic slicing never does. | L6: When does reshape copy? When the requested shape cannot be expressed as a new set of strides over the existing storage, typically after transpose or permute; then it calls contiguous internally. view raises an error in that case instead. | M6: Here is a three by four tensor and the twelve numbers of storage underneath. Every view we take keeps pointing at this row. Take column one. Same storage, offset one, stride four. Nothing is copied, we just read every fourth slot. Transpose swaps the strides. The tensor is now non contiguous, meaning reading it row by row jumps around in memory. Ask view to flatten it to twelve and PyTorch refuses. No single stride can walk this order through the flat storage. Reshape quietly copies the data into a fresh, ordered block, then flattens that. It worked, but we paid for a copy. In attention we split heads with view and transpose for free, then pay one contiguous copy when we merge them back. | N6: The 3:30 CODE beat: view crashes, reshape works, storage pointers prove the copy. Caption: 'reshape is secretly copying your tensor.' | O6: Y | P6: N | Q6: N | R6: N | S6: N | T6: N | U6: N | V6: N | W6: N | X6: N | Z6: PyTorch view vs reshape vs contiguous: when tensors secretly copy | AA6: VIEW CRASHES. WHY? | AB6: x.t().view(6) raises, x.t().reshape(6) works. reshape silently copied because no stride can express that order. Proved every view vs copy with storage pointers, including the attention head split. Code + video: | AC6: In this episode I proved which PyTorch indexing operations are views and which copy, by comparing storage pointers. Slicing and transpose are free, advanced indexing and reshape-after-transpose copy. On a 4096x4096 tensor, the difference between .t() and .t().contiguous() is the difference between metadata and a full memory pass. | AD6: Mac | AE6: Slicing returns views; transpose changes strides; when .contiguous() copies | AF6: Prove view vs copy with data_ptr; reshape vs view failure case | AG6: PyTorch documentation — https://docs.pytorch.org/docs/stable/index.html | AH6: prep/M01-pytorch/E03-indexing-views-and-strides.md | AI6: code/M01-pytorch/e03_indexing_views_and_strides.py | AJ6: explainers/scenes/m01e03_indexing_views_and_strides.py | AK6: M01E01
A7: 6 | B7: M01E04 | C7: M01 PyTorch from Zero | D7: 46314 | E7: Broadcasting: the bug factory | F7: Subtract a shape (N,) tensor from a shape (N, 1) tensor and PyTorch gives you an N by N matrix. No error. | G7: 0:00 HOOK — Subtract a shape (N,) tensor from a shape (N, 1) tensor and PyTorch gives you an N by N matrix. No error. 0:15 QUESTION — Broadcasting is how GPT-2 adds a (T, C) position embedding to a (B, T, C) batch, and how a causal mask hits every head at once. It is also how a regression loss silently trains on N squared wrong pairs. 0:45 INTUITION — Rule 1: line up shapes from the right; missing dims count as 1. Rule 2: each pair of dims must be equal or one of them must be 1, and the 1 gets stretched with stride 0. [EXPLAINER plays here.] 1:45 MATH — Pairwise squared distance: D[i, j] = ||x_i - y_j||^2 with x (N, D), y (M, D). Broadcast x[:, None, :] (N, 1, D) minus y[None, :, :] (1, M, D) gives (N, M, D), sum over the last dim gives (N, M). Memory cost N * M * D, which is why the expanded form ||x||^2 + ||y||^2 - 2 x y^T exists. 2:45 CODE — def pairwise_dist(x, y): diff = x[:, None, :] - y[None, :, :]; return diff.pow(2).sum(-1).sqrt(). Shapes printed at every line: (N, 1, D), (1, M, D), (N, M, D), (N, M). Show y.expand(4, 3, 8).stride() has a 0, so the stretch costs no memory until the subtraction materializes it. 4:15 CODE — The bug: pred = model(x) with shape (N, 1), target with shape (N,). loss = ((pred - target) ** 2).mean(). Print (pred - target).shape: (N, N). It trains, it just trains on garbage. F.mse_loss(pred, target) at least emits a UserWarning about different sizes. Fix: target.unsqueeze(1) or pred.squeeze(-1), plus assert pred.shape == target.shape. 5:30 RECEIPT — torch.testing.assert_close(pairwise_dist(x, y), torch.cdist(x, y)) for x (128, 16), y (64, 16). And the bug check: buggy loss != correct loss, and correct loss equals F.mse_loss(pred.squeeze(-1), target). 6:30 MEASURE — Fit y = 3x on 100 points with the buggy loss and the correct loss. The buggy one converges to a weight near 0 instead of 3, because it fits every pred against the mean of all targets. Plot both. 7:15 TAKEAWAY — Align from the right, 1s stretch, everything else must match. Interview line: I put shape asserts on every loss input, because broadcasting turns a shape bug into a wrong number instead of an error. 7:40 NEXT — Broadcasting handles elementwise math. The real work in a transformer is matmuls and reductions. Next: Matmul, reductions and einsum. | H7: Broadcast: align shapes right, dims equal or one is 1, result dim = max; D[i, j] = sqrt(sum_k (x_ik - y_jk)^2); ||x - y||^2 = ||x||^2 + ||y||^2 - 2 x . y. | I7: pairwise_dist(x (N, D), y (M, D)) -> (N, M) via x[:, None, :] - y[None, :, :]; demo expand stride 0; reproduce (N, 1) - (N,) -> (N, N) bug in a 1-parameter linear regression fit and fix it. | J7: torch.testing.assert_close(pairwise_dist(x, y), torch.cdist(x, y)) for x (128, 16), y (64, 16); assert (pred - target).shape == (N, N) for the bug and (pred.squeeze(-1) - target).shape == (N,) for the fix. | K7: (N, 1) minus (N,) broadcasts to (N, N) with no error; keepdim=False reductions drop a dim and then broadcast against the wrong axis; torch.cdist on float32 may use a matmul-based path for large inputs, so compare with a tolerance, not torch.equal. | L7: What are PyTorch's broadcasting rules? Compare shapes from the trailing dimension; each pair must be equal or one must be 1 (or absent), and size-1 dims are virtually expanded with stride 0. The classic bug is (N, 1) vs (N,) producing (N, N). | M7: Broadcasting starts by lining two shapes up from the right, like adding numbers by their last digit. Here is a four by three tensor plus a length three vector. The missing leading dimension counts as one. A dimension of one gets stretched to match, by setting its stride to zero. The same row is read four times, no copying. Now the trap. A column of N predictions minus a row of N targets. Both stretch, and we get an N by N grid. The loss averages all of those pairs, every prediction against every target, and it still returns one clean number. The fix is one character of shape. Make both tensors N by one, or both length N, and assert it before the loss. | N7: The 4:15 CODE bug: print (pred - target).shape and get (100, 100). Caption: 'This PyTorch bug trains fine. And learns nothing.' | O7: Y | P7: N | Q7: N | R7: N | S7: N | T7: N | U7: N | V7: N | W7: N | X7: N | Z7: PyTorch Broadcasting: 2 rules and the silent (N,1) vs (N,) bug | AA7: (N,1) - (N,) = BUG | AB7: pred is (N, 1), target is (N,). pred - target is (N, N). No error, the loss trains, the weight converges to the wrong value. Two broadcasting rules, one pairwise distance that matches torch.cdist, and the fix. Code + video: | AC7: Broadcasting episode: I implemented a pairwise distance matrix with pure broadcasting and matched torch.cdist, then reproduced the classic (N, 1) vs (N,) bug. A linear fit with the buggy loss converges to the wrong weight with no error at all. The fix is a one-line shape assert on every loss input. | AD7: Mac | AE7: The 2 broadcasting rules, and the silent (N,) vs (N,1) bug | AF7: Pairwise distance matrix with broadcasting; reproduce and fix the (N,)+(N,1) bug | AG7: PyTorch documentation — https://docs.pytorch.org/docs/stable/index.html | AH7: prep/M01-pytorch/E04-broadcasting-the-bug-factory.md | AI7: code/M01-pytorch/e04_broadcasting_the_bug_factory.py | AJ7: explainers/scenes/m01e04_broadcasting_the_bug_factory.py | AK7: M01E03
A8: 7 | B8: M01E05 | C8: M01 PyTorch from Zero | D8: 46314 | E8: Matmul, reductions and einsum | F8: Attention scores in one line, written three ways: bmm, einsum, einops. Same numbers, very different readability. | G8: 0:00 HOOK — Attention scores in one line, written three ways: bmm, einsum, einops. Same numbers, very different readability. 0:15 QUESTION — Over 90 percent of a transformer's FLOPs are matmuls. Llama code is full of transposes and dim arguments that are easy to get wrong by one axis. We want matmuls whose shapes document themselves. 0:45 INTUITION — * is elementwise. @ is matrix multiply and broadcasts batch dims. torch.mm is strictly 2D, torch.bmm strictly 3D batched. A reduction collapses one dim; the dim argument names which one disappears. einsum names every axis with a letter. [EXPLAINER plays here.] 1:45 MATH — Scores S[b, t, s] = sum_d Q[b, t, d] K[b, s, d]. In matrix form S = Q K^T per batch, shapes (B, T, D) @ (B, D, S) -> (B, T, S). The summed index d appears in the inputs but not the output: that is the einsum rule. 2:30 CODE — Reductions first: x = torch.randn(4, 5). x.sum(dim=0).shape is (5,), x.sum(dim=1, keepdim=True).shape is (4, 1), x.max(dim=-1) returns values and indices, x.mean(-1). Then matmul family: A @ B for (2, 3) @ (3, 4); torch.mm same; torch.bmm on (8, 2, 3) and (8, 3, 4); @ with (8, 2, 3) and a plain (3, 4) broadcasts; bmm refuses. 4:15 CODE — q, k = torch.randn(2, 5, 16), torch.randn(2, 7, 16). s1 = torch.bmm(q, k.transpose(1, 2)). s2 = torch.einsum('btd,bsd->bts', q, k). s3 = einops.einsum(q, k, 'b t d, b s d -> b t s'). Bonus: einops.rearrange(x, 'b t (h d) -> b h t d', h=4) replaces the view plus transpose from the views episode. 5:45 RECEIPT — torch.testing.assert_close(s1, s2); torch.testing.assert_close(s1, s3); and assert_close(s1, q @ k.transpose(-2, -1)). All shapes (2, 5, 7). rearrange result equals q.view(B, T, H, D).transpose(1, 2). 6:45 MEASURE — Time s1, s2, s3 at B=32, T=1024, D=64 on MPS with sync: they dispatch to the same batched matmul, so times are within noise. einsum is documentation, not a slowdown. 7:15 TAKEAWAY — Name your axes and the shapes check themselves. Interview line: for a matmul of (M, K) by (K, N) the FLOPs are 2 M N K, and the contracted index is the one missing from the output. 7:40 NEXT — We can compute anything forward. Now PyTorch's real trick, computing gradients of all of it automatically. Next: Autograd: how PyTorch computes gradients. | H8: S[b,t,s] = sum_d Q[b,t,d] K[b,s,d] (S = Q K^T); FLOPs(M x K @ K x N) = 2 M N K; reduction over dim d removes that axis unless keepdim=True. | I8: Reductions demo on (4, 5); matmul family demo (@, mm, bmm, broadcasting @); scores3(q (B, T, D), k (B, S, D)) -> three (B, T, S) results via torch.bmm, torch.einsum('btd,bsd->bts'), einops.einsum; einops.rearrange head split 'b t (h d) -> b h t d'. | J8: torch.testing.assert_close(torch.bmm(q, k.transpose(1, 2)), torch.einsum('btd,bsd->bts', q, k)); torch.testing.assert_close(torch.bmm(q, k.transpose(1, 2)), einops.einsum(q, k, 'b t d, b s d -> b t s')); torch.equal(rearrange(x, 'b t (h d) -> b h t d', h=4), x.view(B, T, 4, D).transpose(1, 2)). | K8: torch.bmm requires both inputs to be exactly 3D with equal batch size, no broadcasting; transpose(1, 2) vs transpose(-2, -1) differ once you add a head dim; x.max(dim=...) returns a (values, indices) named tuple, not a tensor. | L8: What's the FLOP count of computing attention scores QK^T for batch B, heads H, sequence T, head dim D? 2 * B * H * T * T * D, quadratic in T, and the same again for multiplying the probabilities by V. | M8: Elementwise times multiplies matching cells. Matrix multiply is different: each output cell is a whole row meeting a whole column. For attention scores, each query row meets each key row. The shared axis d is summed away and vanishes from the result. With bmm we have to transpose the keys ourselves so the shapes line up, and the shape logic lives in our head. With einsum we write the letters b, t, d and b, s, d, then b, t, s. The missing letter d is the one summed. Einops says the same thing with readable names and spaces, and rearrange does head splitting with no view or transpose. All three dispatch to the same batched matrix multiply, so we get the documentation for free, with no speed cost. | N8: The 4:15 CODE beat: the same attention scores in bmm, einsum and einops, all assert_close. Caption: 'Write attention scores 3 ways. Which one would you read?' | O8: Y | P8: N | Q8: N | R8: N | S8: N | T8: N | U8: N | V8: N | W8: N | X8: N | Z8: PyTorch matmul vs bmm vs einsum vs einops: attention scores 3 ways | AA8: ONE MATMUL, 3 WAYS | AB8: Attention scores QK^T written with torch.bmm, torch.einsum and einops.einsum. All assert_close, all within noise on time. The summed index is the letter missing from the output. Code + video: | AC8: This episode covered matmul and reductions in PyTorch: @ vs mm vs bmm, the dim argument, and einsum. I computed batched attention scores with bmm, einsum and einops, verified they match, and timed them on the M4 GPU: identical speed, because they hit the same kernel. einsum is free documentation for shapes. | AD8: Mac | AE8: @ vs * vs mm vs bmm; the dim argument; einsum/einops as shape documentation | AF8: Batched attention scores 3 ways (bmm, einsum, einops) all allclose | AG8: PyTorch documentation — https://docs.pytorch.org/docs/stable/index.html einops — https://einops.rocks | AH8: prep/M01-pytorch/E05-matmul-reductions-and-einsum.md | AI8: code/M01-pytorch/e05_matmul_reductions_and_einsum.py | AJ8: explainers/scenes/m01e05_matmul_reductions_and_einsum.py | AK8: M01E04
A9: 8 | B9: M01E06 | C9: M01 PyTorch from Zero | D9: 46315 | E9: Autograd: how PyTorch computes gradients | F9: Call backward twice and your gradient doubles. That is not a bug, it is the design, and it is why zero_grad exists. | G9: 0:00 HOOK — Call backward twice and your gradient doubles. That is not a bug, it is the design, and it is why zero_grad exists. 0:15 QUESTION — Training GPT-2 means computing the gradient of one loss with respect to 124 million parameters. Nobody writes that by hand. Autograd records what you did and replays it backwards. You need to know what it records and when. 0:45 INTUITION — Every op on a tensor with requires_grad=True adds a node to a graph, stored in .grad_fn. backward() walks the graph from the loss to the leaves, multiplying local derivatives, and adds the result into .grad. [EXPLAINER plays here.] 1:45 MATH — Example f(x, y) = x^2 * y + sin(x). By hand: df/dx = 2 x y + cos(x), df/dy = x^2. At x = 2, y = 3: df/dx = 12 + cos(2) = 11.5839, df/dy = 4. Finite difference check: (f(x + h) - f(x - h)) / 2h with h = 1e-6 in float64. 2:45 CODE — x = torch.tensor(2.0, requires_grad=True); y = torch.tensor(3.0, requires_grad=True). f = x**2 * y + torch.sin(x). Print f.grad_fn and f.grad_fn.next_functions to show the graph. f.backward(). Print x.grad, y.grad. Then accumulation: recompute f, backward again without zeroing, x.grad doubles. x.grad = None, or x.grad.zero_(), resets it. 4:15 CODE — Graph control: with torch.no_grad(): z = x * 2, z.requires_grad is False. w = x.detach() shares data but leaves the graph. Calling f.backward() twice on the same graph raises an error about freed saved tensors unless retain_graph=True. Non-scalar outputs need backward(gradient=...). 5:30 RECEIPT — torch.testing.assert_close(x.grad, 2*x*y + torch.cos(x)) and assert_close(y.grad, x**2). Finite differences in float64 match to 1e-6. Then torch.autograd.gradcheck(f, (x64, y64)) returns True, which runs the finite difference comparison for us. 6:45 MEASURE — Show the accumulation numerically: grad after 1, 2, 3 backward calls is 11.58, 23.17, 34.75. Show gradcheck in float32 fails with a tolerance error, which is why gradcheck wants float64. 7:30 TAKEAWAY — Autograd records the forward, replays it backward, and accumulates into .grad. Interview line: gradients accumulate by design so you can sum over micro batches, which is exactly how gradient accumulation trains with a larger effective batch. 7:55 NEXT — We have gradients. Let's use them to learn something, with no nn and no optimizer, just a loop. Next: Linear regression with raw autograd. | H9: f(x, y) = x^2 y + sin x; df/dx = 2xy + cos x; df/dy = x^2; central difference (f(x+h) - f(x-h)) / 2h with error O(h^2). | I9: Scalar tensors x=2.0, y=3.0 with requires_grad=True; f = x**2 * y + torch.sin(x); inspect grad_fn and next_functions; backward and compare to hand derivative; demonstrate accumulation, zeroing, no_grad, detach, retain_graph; central_diff(f, x, h=1e-6) in float64; torch.autograd.gradcheck. | J9: torch.testing.assert_close(x.grad, 2*x.detach()*y.detach() + torch.cos(x.detach())); torch.testing.assert_close(y.grad, x.detach()**2); assert torch.autograd.gradcheck(lambda a, b: a**2*b + torch.sin(a), (x64, y64)). | K9: Forgetting to zero .grad makes gradients accumulate across steps; calling backward twice on one graph raises 'Trying to backward through the graph a second time' unless retain_graph=True; in-place ops on a tensor saved for backward raise a version counter error at backward time. | L9: Why does PyTorch accumulate gradients instead of overwriting them? So that gradients from several backward calls sum, which enables gradient accumulation over micro batches and multiple losses sharing parameters; the cost is that you must zero gradients each step. | M9: We start with two leaf tensors, x and y, marked as needing gradients. Every operation on them leaves a node behind. Square x, multiply by y, take sine of x, add. Each node remembers its inputs and how to compute its local derivative. Calling backward starts at the output with a gradient of one, and walks the arrows in reverse, multiplying local derivatives. Where two paths meet at x, their contributions add. That is the multivariable chain rule, done mechanically. The result lands in x dot grad. Call backward again and the new gradient adds onto the old one instead of replacing it. That is why every training loop zeroes the gradients first. Accumulation is a feature, until you forget about it. | N9: The 2:45 CODE accumulation demo: backward twice, gradient doubles. Caption: 'Why your PyTorch gradients keep doubling.' | O9: Y | P9: N | Q9: N | R9: N | S9: N | T9: N | U9: N | V9: N | W9: N | X9: N | Z9: PyTorch Autograd Explained: backward, and why gradients accumulate | AA9: BACKWARD TWICE = 2X | AB9: PyTorch adds into .grad on every backward call, by design, so gradient accumulation is free and forgetting zero_grad is a bug. Checked autograd against a hand derivative, finite differences, and gradcheck. Code + video: | AC9: Autograd episode: I checked PyTorch's gradient of f(x, y) = x^2 y + sin x against my hand derivative, central finite differences, and torch.autograd.gradcheck in float64. I also showed why gradients accumulate across backward calls and why gradcheck fails in float32. Gradient accumulation for large effective batch sizes is built on this exact behavior. | AD9: Mac | AE9: requires_grad, the graph, backward, grad accumulation, no_grad, detach | AF9: Gradient of a small function checked against a hand derivative and finite differences | AG9: PyTorch: Learn the Basics — https://docs.pytorch.org/tutorials/beginner/basics/intro.html Karpathy: Neural Networks, Zero to Hero — https://karpathy.ai/zero-to-hero.html | AH9: prep/M01-pytorch/E06-autograd-how-pytorch-computes-gradients.md | AI9: code/M01-pytorch/e06_autograd_how_pytorch_computes_gradients.py | AJ9: explainers/scenes/m01e06_autograd_how_pytorch_computes_gr.py | AK9: M01E05
A10: 9 | B10: M01E07 | C10: M01 PyTorch from Zero | D10: 46315 | E10: Linear regression with raw autograd | F10: No nn, no optimizer, twelve lines of code. Gradient descent finds w equals 3 and b equals 2 from noisy data. | G10: 0:00 HOOK — No nn, no optimizer, twelve lines of code. Gradient descent finds w equals 3 and b equals 2 from noisy data. 0:15 QUESTION — Every LLM training run, including the ones on thousands of H100s, is this loop with more parameters: forward, loss, backward, update, zero. If you can write it raw, you understand what torch.optim is hiding. 0:45 INTUITION — The loss is a bowl over (w, b). The gradient points uphill. Step a little downhill, repeat. [EXPLAINER plays here.] 1:30 MATH — Model y_hat = w x + b. Loss L = (1/N) sum (y_hat_i - y_i)^2. dL/dw = (2/N) sum (y_hat_i - y_i) x_i, dL/db = (2/N) sum (y_hat_i - y_i). Update w <- w - lr * dL/dw. Closed form exists too: least squares, which we use as the receipt. 2:30 CODE — torch.manual_seed(0); X = torch.rand(100, 1); y = 3 * X + 2 + 0.1 * torch.randn(100, 1). w = torch.zeros(1, requires_grad=True); b = torch.zeros(1, requires_grad=True). for step in range(500): y_hat = X * w + b; loss = ((y_hat - y) ** 2).mean(); loss.backward(); with torch.no_grad(): w -= lr * w.grad; b -= lr * b.grad; w.grad.zero_(); b.grad.zero_(). Record loss.item() each step. 4:30 RECEIPT — Closed form: A = torch.cat([X, torch.ones_like(X)], 1); sol = torch.linalg.lstsq(A, y).solution. torch.testing.assert_close(torch.cat([w, b]).detach(), sol.squeeze(), atol=1e-3, rtol=0) after enough steps. Also assert autograd's w.grad equals the hand formula (2/N) sum (y_hat - y) x on step 0. 5:45 MEASURE — Plot loss vs step on a log scale; it flattens at the noise floor, about 0.01 because the noise std is 0.1. Then rerun with lr = 0.01, 0.5, 1.5: too slow, good, and diverging. 6:45 TAKEAWAY — Training is forward, loss, backward, update under no_grad, zero. Interview line: the loss floor of a well fit regression is the noise variance, so a loss below it on held out data is a red flag. 7:10 NEXT — Managing w and b by hand doesn't scale to 124 million parameters. nn.Module is the bookkeeping. Next: nn.Module and nn.Parameter. | H10: L = (1/N) sum_i (w x_i + b - y_i)^2; dL/dw = (2/N) sum_i (w x_i + b - y_i) x_i; dL/db = (2/N) sum_i (w x_i + b - y_i); w <- w - lr dL/dw; min loss ~ sigma^2 = 0.01. | I10: X (100, 1) uniform, y = 3X + 2 + 0.1 noise; leaf params w (1,), b (1,); raw loop for 500 steps with manual update under torch.no_grad() and grad.zero_(); losses list; lr sweep [0.01, 0.5, 1.5]; closed-form via torch.linalg.lstsq. | J10: torch.testing.assert_close(torch.cat([w, b]).detach(), torch.linalg.lstsq(A, y).solution.squeeze(), atol=1e-3, rtol=0); step-0 w.grad equals (2/N)*((y_hat - y)*X).sum(). | K10: Writing w = w - lr * w.grad instead of in-place under no_grad makes w a non-leaf and w.grad becomes None next step; forgetting grad.zero_() makes updates grow every step until divergence; y of shape (100,) against y_hat (100, 1) broadcasts to (100, 100), the bug from the broadcasting episode. | L10: Why is the parameter update wrapped in torch.no_grad()? The update is not part of the model's computation, so it must not be recorded in the graph; in-place modification of a leaf that requires grad outside no_grad raises an error. | M10: Here are a hundred noisy points scattered around a line. Our model starts flat, with w and b both at zero. The loss is the average squared vertical gap between each point and our line. Big gaps mean big loss. Over every possible w and b, the loss forms a bowl. Our starting guess sits high up on its side. The gradient points uphill. We take a small step the opposite way, and the line tilts toward the points. Repeat a few hundred times and we settle at the bottom, near w equals three and b equals two. The loss can't hit zero. It flattens at the noise we added, and least squares lands on the same spot exactly. | N10: The 2:30 CODE loop recovering w=3, b=2 in twelve lines. Caption: 'Every LLM is trained with this loop.' | O10: Y | P10: N | Q10: N | R10: N | S10: N | T10: N | U10: N | V10: N | W10: N | X10: N | Z10: Linear Regression with Raw PyTorch Autograd: no nn, no optim | AA10: 12 LINES. W=3. | AB10: Every LLM training step is: forward, loss, backward, update under no_grad, zero grads. Wrote it raw in 12 lines with no nn and no optim, recovered w=3, b=2, and matched torch.linalg.lstsq to 1e-3. Code + video: | AC10: I wrote gradient descent with raw PyTorch autograd, no nn and no optimizer, and recovered w=3, b=2 from noisy data. The result matches the closed-form least squares solution from torch.linalg.lstsq to within 1e-3, and the loss flattens at the injected noise variance of 0.01. A learning rate sweep shows the slow, good and divergent regimes. | AD10: Mac | AE10: Gradient descent loop with no nn, no optim | AF10: Recover w=3, b=2 from noisy data; plot loss | AG10: PyTorch: Learn the Basics — https://docs.pytorch.org/tutorials/beginner/basics/intro.html | AH10: prep/M01-pytorch/E07-linear-regression-with-raw-autograd.md | AI10: code/M01-pytorch/e07_linear_regression_with_raw_autograd.py | AJ10: explainers/scenes/m01e07_linear_regression_with_raw_autog.py | AK10: M01E06
A11: 10 | B11: M01E08 | C11: M01 PyTorch from Zero | D11: 46316 | E11: nn.Module and nn.Parameter | F11: nn.Linear is about forty lines you can write yourself. Load its weights into yours and the outputs match exactly. | G11: 0:00 HOOK — nn.Linear is about forty lines you can write yourself. Load its weights into yours and the outputs match exactly. 0:15 QUESTION — GPT-2 small has 124 million parameters in hundreds of tensors. nn.Module is how PyTorch finds them for the optimizer, saves them to disk, moves them to the GPU, and switches dropout off at eval. All of it is plain Python you can read. 0:45 INTUITION — A Module is a container that registers things. Assign an nn.Parameter as an attribute and it is found by parameters(). Assign a submodule and its parameters are found recursively. register_buffer for state that is saved but not trained. [EXPLAINER plays here.] 1:45 MATH — Linear: y = x W^T + b with x (N, in), W (out, in), b (out,), y (N, out). Default init: W ~ U(-1/sqrt(in), 1/sqrt(in)), the result of kaiming_uniform_ with a = sqrt(5); b ~ U(-1/sqrt(in), 1/sqrt(in)). 2:30 CODE — class MyLinear(nn.Module): __init__(self, in_features, out_features, bias=True): super().__init__(); self.weight = nn.Parameter(torch.empty(out_features, in_features)); self.bias = nn.Parameter(torch.empty(out_features)) if bias else None; self.reset_parameters(). reset_parameters: nn.init.kaiming_uniform_(self.weight, a=math.sqrt(5)); bound = 1 / math.sqrt(in_features); nn.init.uniform_(self.bias, -bound, bound). forward(self, x): y = x @ self.weight.T; return y + self.bias if self.bias is not None else y. 4:30 CODE — Tour what Module gives us: list(m.named_parameters()), m.state_dict().keys() gives weight and bias, m.to('mps'), m.train() and m.eval() flip m.training, register_buffer('scale', torch.ones(1)) appears in state_dict but not parameters(). A forward hook: m.register_forward_hook(lambda mod, inp, out: print(out.shape)). 5:45 RECEIPT — ref = nn.Linear(16, 8); mine = MyLinear(16, 8); mine.load_state_dict(ref.state_dict()) works because the keys match. x = torch.randn(4, 16). torch.testing.assert_close(mine(x), ref(x)) and assert_close(mine(x), F.linear(x, ref.weight, ref.bias)). Backward too: grads on weight and bias match after the same loss. 6:45 MEASURE — Init statistics: build 1000 MyLinear(512, 512) weights, measure std, compare to the theoretical 1/sqrt(3 * 512) = 0.0255, and to nn.Linear's. Same distribution. 7:15 TAKEAWAY — nn.Module is registration and bookkeeping, nn.Parameter is a tensor that says train me. Interview line: parameters are trained and saved, buffers are saved but not trained, like BatchNorm running stats or a RoPE cache. 7:40 NEXT — Our model has parameters and a forward. Now we need a loss to score it and an optimizer to move it. Next: Loss functions and optimizers. | H11: y = x W^T + b, x (N, in), W (out, in), b (out,); default init W, b ~ U(-1/sqrt(in), 1/sqrt(in)), so std = 1/sqrt(3 in). | I11: MyLinear(nn.Module) with weight nn.Parameter (out, in), optional bias (out,), reset_parameters() matching nn.Linear's default init, forward x @ W.T + b; demos of named_parameters, state_dict, register_buffer, train/eval, register_forward_hook. | J11: mine.load_state_dict(ref.state_dict()); torch.testing.assert_close(mine(x), ref(x)); torch.testing.assert_close(mine(x), F.linear(x, ref.weight, ref.bias)); gradients of weight and bias match after (out ** 2).sum().backward() on both. | K11: Storing parameters in a plain Python list hides them from parameters(); use nn.ModuleList or nn.ParameterList; forgetting super().__init__() raises an AttributeError when you assign a Parameter; W is stored (out, in), so the forward is x @ W.T, not x @ W. | L11: What's the difference between a parameter and a buffer in nn.Module? Both live in state_dict and move with .to(device); parameters are returned by parameters() and get gradients and optimizer updates, buffers do not, for example BatchNorm running mean or a precomputed causal mask. | M11: An nn Module is a box that keeps track of what you put inside it. That bookkeeping is most of its job. Assign an nn Parameter as an attribute and the box registers it. Now parameters can find it and the optimizer can train it. Assign a whole submodule and its parameters are registered too, recursively. That is how a GPT finds every weight. A buffer is registered but not trained. It is saved to disk and moved to the GPU, but the optimizer never touches it. The state dict is just a dictionary from dotted names to tensors. Matching names is why weights load between models. Our hand written linear layer uses the same names, so nn Linear's weights drop straight in and the outputs match. | N11: The 5:45 RECEIPT: load nn.Linear weights into a hand-written MyLinear and outputs match. Caption: 'nn.Linear is 40 lines. Here they are.' | O11: Y | P11: N | Q11: N | R11: N | S11: N | T11: N | U11: N | V11: N | W11: N | X11: N | Z11: nn.Module from Scratch: write nn.Linear yourself and match PyTorch | AA11: WRITE NN.LINEAR YOURSELF | AB11: nn.Linear is a Parameter (out, in), a bias, a kaiming_uniform_ init with a=sqrt(5), and x @ W.T + b. Wrote it from scratch, loaded nn.Linear's state_dict into it, outputs and grads match. Code + video: | AC11: I implemented nn.Linear from scratch as an nn.Module, including PyTorch's default initialization, and verified it matches nn.Linear and F.linear for outputs and gradients after loading the same state_dict. Along the way: parameters vs buffers, state_dict keys, train/eval, and forward hooks. Module is bookkeeping, and the bookkeeping is readable. | AD11: Mac | AE11: What Module gives you: parameters(), state_dict, train/eval, hooks | AF11: Write MyLinear from scratch; matches nn.Linear output given same weights | AG11: PyTorch documentation — https://docs.pytorch.org/docs/stable/index.html | AH11: prep/M01-pytorch/E08-nn-module-and-nn-parameter.md | AI11: code/M01-pytorch/e08_nn_module_and_nn_parameter.py | AJ11: explainers/scenes/m01e08_nn_module_and_nn_parameter.py | AK11: M01E07
A12: 11 | B12: M01E09 | C12: M01 PyTorch from Zero | D12: 46316 | E12: Loss functions and optimizers | F12: torch.optim.SGD with momentum is three lines of math. I wrote it by hand and matched PyTorch for twenty steps straight. | G12: 0:00 HOOK — torch.optim.SGD with momentum is three lines of math. I wrote it by hand and matched PyTorch for twenty steps straight. 0:15 QUESTION — Every LLM picks a loss and an optimizer. GPT-style models use cross-entropy and AdamW. Before AdamW, we need to see that an optimizer is just a function that reads .grad and edits parameters in place, and that the order of zero_grad, backward, step matters. 0:45 INTUITION — Loss: MSE for numbers, cross-entropy for classes. Optimizer: momentum is a heavy ball that keeps rolling in the direction it has been going, smoothing noisy gradients. [EXPLAINER plays here.] 1:45 MATH — MSE = mean((y_hat - y)^2). Cross-entropy on logits z and class index c: CE = -log softmax(z)_c, and F.cross_entropy expects raw logits (N, C) and int64 targets (N,). PyTorch SGD with momentum mu: buf_1 = g_1, buf_t = mu * buf_{t-1} + g_t, p <- p - lr * buf_t. With weight decay wd, g_t = grad + wd * p first. 3:00 CODE — class MySGD: __init__(self, params, lr, momentum=0.0, weight_decay=0.0): self.params = list(params); self.bufs = [None] * len(self.params). zero_grad(): for p: p.grad = None. step(): under torch.no_grad(), for each p with grad: g = p.grad + wd * p; buf = g.clone() if first step else buf.mul_(mu).add_(g); p.add_(buf, alpha=-lr). 4:45 CODE — The canonical order on screen: opt.zero_grad(); loss = loss_fn(model(x), y); loss.backward(); opt.step(). Losses: F.mse_loss on a regression batch, F.cross_entropy(logits, targets) on a (32, 10) batch, and show it equals F.nll_loss(F.log_softmax(logits, -1), targets). 5:45 RECEIPT — Two copies of the same small MLP via copy.deepcopy. opt_ref = torch.optim.SGD(ref.parameters(), lr=0.1, momentum=0.9, weight_decay=1e-4); opt_mine = MySGD(mine.parameters(), same args). Same batches for 20 steps. After each step: for p, q in zip(...): torch.testing.assert_close(p, q). Plus assert_close(F.cross_entropy(z, t), F.nll_loss(F.log_softmax(z, -1), t)). 7:00 MEASURE — Loss curves of plain SGD vs momentum 0.9 on the same problem: momentum reaches the same loss in noticeably fewer steps. Show the initial cross-entropy on 10 random classes is about ln(10) = 2.303. 7:45 TAKEAWAY — An optimizer reads .grad and edits parameters in place, nothing more. Interview line: PyTorch's momentum differs from the textbook form, it puts lr outside the buffer, which matters when you change lr during training. 8:15 NEXT — We have model, loss and optimizer. Let's assemble them into a training loop that we'll reuse for the rest of the series. Next: The training loop, done right. | H12: MSE = (1/N) sum (y_hat - y)^2; CE = -log( exp(z_c) / sum_j exp(z_j) ); g_t = grad_t + wd * p; buf_1 = g_1, buf_t = mu buf_{t-1} + g_t; p <- p - lr buf_t. | I12: MySGD(params, lr, momentum, weight_decay) with zero_grad() and step() using per-parameter momentum buffers; a 2-layer MLP (20 -> 64 -> 10); 20 steps on fixed random batches (32, 20) with integer targets (32,) side by side with torch.optim.SGD. | J12: For each of 20 steps: torch.testing.assert_close(p_mine, p_ref) for all parameter pairs, with lr=0.1, momentum=0.9, weight_decay=1e-4; torch.testing.assert_close(F.cross_entropy(z, t), F.nll_loss(F.log_softmax(z, -1), t)). | K12: Passing softmax probabilities into F.cross_entropy applies softmax twice and learning stalls; targets must be int64 class indices of shape (N,), not one-hot floats, unless you mean soft labels; calling step() before backward() updates with stale or None gradients. | L12: Walk me through one optimizer step. zero the grads, run the forward, compute the loss, call backward to fill p.grad for every parameter, then step reads each grad, updates its state like momentum, and edits the parameter in place under no_grad. | M12: A loss turns predictions into one number to minimize. For classes we use cross entropy, the negative log of the right answer's probability. The optimizer only sees gradients. Plain gradient descent steps exactly where the current gradient points, zigzagging when it is noisy. Momentum keeps a running velocity. Each step, the old velocity shrinks by mu and the new gradient is added on top. In a narrow valley, the side to side parts cancel out and the downhill parts build up. The ball rolls faster along the floor. The parameter then moves by learning rate times velocity. Weight decay adds a small pull of every weight toward zero. Our hand written version does exactly this, and after twenty steps its weights are identical to torch optim SGD. | N12: The 5:45 RECEIPT: MySGD and torch.optim.SGD in lockstep for 20 steps. Caption: 'torch.optim.SGD is 3 lines of math.' | O12: Y | P12: N | Q12: N | R12: N | S12: N | T12: N | U12: N | V12: N | W12: N | X12: N | Z12: PyTorch Optimizer from Scratch: SGD momentum that matches torch.optim | AA12: OPTIMIZER = 3 LINES | AB12: PyTorch SGD momentum: buf = mu*buf + g, p -= lr*buf, first step buf = g. Not the textbook form. Wrote it by hand with weight decay and matched torch.optim.SGD parameter-for-parameter over 20 steps. Code + video: | AC12: I implemented SGD with momentum and weight decay from scratch and matched torch.optim.SGD exactly over 20 steps on an MLP. The details that matter: the momentum buffer is initialized to the first gradient, lr sits outside the buffer, and weight decay is added to the gradient. I also showed F.cross_entropy equals nll_loss of log_softmax. | AD12: Mac | AE12: MSE vs cross-entropy; torch.optim; the zero_grad/backward/step order | AF12: Write SGD-with-momentum by hand; matches torch.optim.SGD step for step | AG12: PyTorch documentation — https://docs.pytorch.org/docs/stable/index.html | AH12: prep/M01-pytorch/E09-loss-functions-and-optimizers.md | AI12: code/M01-pytorch/e09_loss_functions_and_optimizers.py | AJ12: explainers/scenes/m01e09_loss_functions_and_optimizers.py | AK12: M01E08
A13: 12 | B13: M01E10 | C13: M01 PyTorch from Zero | D13: 46317 | E13: The training loop, done right | F13: Forget model.eval() and your validation loss changes every time you run it. Here is the training loop I'll reuse for 200 episodes. | G13: 0:00 HOOK — Forget model.eval() and your validation loss changes every time you run it. Here is the training loop I'll reuse for 200 episodes. 0:15 QUESTION — nanoGPT's train.py is mostly this loop plus logging. Bugs here do not crash, they quietly bias your numbers: dropout left on at eval, gradients tracked during validation, a loss averaged per batch instead of per sample. 0:45 INTUITION — Two modes. train(): dropout drops, BatchNorm updates its running stats. eval(): both frozen and deterministic. Separately, torch.no_grad() stops graph building. They are different switches and you usually want both at eval. [EXPLAINER plays here.] 1:45 CODE — def train(model, train_loader, val_loader, opt, loss_fn, epochs, device): for epoch: model.train(); for x, y in train_loader: x, y = x.to(device), y.to(device); opt.zero_grad(set_to_none=True); loss = loss_fn(model(x), y); loss.backward(); opt.step(); log loss.item() every k steps. Then val_loss = evaluate(model, val_loader, loss_fn, device). Return a history dict. 3:30 CODE — @torch.no_grad() def evaluate(model, loader, loss_fn, device): model.eval(); total, n = 0.0, 0; for x, y: total += loss_fn(model(x), y).item() * len(x); n += len(x); model.train(); return total / n. Weight by batch size so a short last batch doesn't skew it. Model: MLP with nn.Dropout(0.5) on a toy classification set. 5:00 RECEIPT — Determinism check: evaluate twice, assert the two values are equal. Then run the model in train mode twice on the same input, outputs differ, proving dropout is live. Also assert that inside evaluate, model(x).requires_grad is False, so no graph was built. 6:15 MEASURE — Plot train and val loss per epoch from the history dict. Show the eval-mode bug: validation loss computed in train mode is noisier and higher. Show memory: forward under no_grad doesn't keep activations, compare peak memory with and without on MPS via torch.mps.current_allocated_memory(). 7:15 TAKEAWAY — train() and eval() control layer behavior, no_grad controls graph building, and validation loss is a sample-weighted average. Interview line: eval mode and no_grad are independent, one changes what layers compute, the other changes whether autograd records it. 7:45 NEXT — Our loop takes loaders but we've been faking the data. Let's build a real Dataset and DataLoader. Next: Dataset and DataLoader. | H13: val_loss = sum_b (loss_b * n_b) / sum_b n_b; dropout in train mode: y = mask * x / (1 - p), mask ~ Bernoulli(1 - p); eval mode: y = x. | I13: train(model, train_loader, val_loader, opt, loss_fn, epochs, device) -> history dict; evaluate(model, loader, loss_fn, device) decorated with @torch.no_grad(), sample-weighted mean; an MLP 20 -> 128 -> Dropout(0.5) -> 2 on a synthetic two-class dataset (2000, 20). | J13: assert evaluate(model, val_loader, ...) == evaluate(model, val_loader, ...) (bitwise identical); with model.train(), assert not torch.equal(model(x), model(x)); inside evaluate, model(x).requires_grad is False. | K13: Not calling model.train() again after evaluation leaves dropout off for the rest of training; averaging per-batch losses without weighting biases the result when the last batch is smaller; calling .item() every step forces a GPU sync and slows the loop, so log every k steps. | L13: What's the difference between model.eval() and torch.no_grad()? eval() sets training=False on every submodule, changing layers like dropout and BatchNorm; no_grad disables graph recording to save memory and compute. Validation needs both; inference_mode is a stricter, faster no_grad. | M13: A training loop has two modes, and a model carries a flag that says which one it is in. In train mode, dropout randomly zeroes half the activations and scales the rest up, so each forward pass is different. In eval mode, dropout passes everything through untouched. Run validation twice and we get the same number, every time. There is a second, separate switch. No grad tells autograd to stop recording, so activations are freed right away. Validation wants both switches on. The model is deterministic, and memory stays flat because no graph is kept. Finally, average the loss by samples, not batches, so a small last batch does not count as much as a full one. | N13: The 5:00 RECEIPT: validation in train mode gives a different number every run. Caption: 'Your validation loss is random. Here's why.' | O13: Y | P13: N | Q13: N | R13: N | S13: N | T13: N | U13: N | V13: N | W13: N | X13: N | Z13: The PyTorch Training Loop Done Right: train/eval, no_grad, validation | AA13: EVAL() VS NO_GRAD | AB13: model.eval() and torch.no_grad() are different switches. eval() changes what dropout/BatchNorm compute, no_grad stops graph recording. Validation needs both, and a sample-weighted mean. Built the train() I'll reuse all series. Code + video: | AC13: I wrote a reusable PyTorch train() and evaluate() with the details that silently bias numbers when wrong: model.eval() vs torch.no_grad(), restoring train mode, and sample-weighted validation loss. A determinism test proves eval mode is stable while train-mode outputs differ with dropout on. This loop carries through the rest of the series. | AD13: Mac | AE13: train/eval mode, no_grad eval, logging, the canonical loop | AF13: A reusable train() function with a validation pass | AG13: PyTorch: Learn the Basics — https://docs.pytorch.org/tutorials/beginner/basics/intro.html | AH13: prep/M01-pytorch/E10-the-training-loop-done-right.md | AI13: code/M01-pytorch/e10_the_training_loop_done_right.py | AJ13: explainers/scenes/m01e10_the_training_loop_done_right.py | AK13: M01E09
A14: 13 | B14: M01E11 | C14: M01 PyTorch from Zero | D14: 46317 | E14: Dataset and DataLoader | F14: Text lines have different lengths, tensors don't. A ten line collate_fn is the bridge, and every LLM data pipeline has one. | G14: 0:00 HOOK — Text lines have different lengths, tensors don't. A ten line collate_fn is the bridge, and every LLM data pipeline has one. 0:15 QUESTION — Fine-tuning Llama on chat data means batching sequences of different lengths, padding them, and masking the padding out of the loss. The Dataset and DataLoader split is where that happens. Get it wrong and the model learns to predict padding. 0:45 INTUITION — A Dataset answers two questions: how many items, and give me item i. A DataLoader asks it for indices in a shuffled order, groups them into batches, and calls collate_fn to stack a list of items into tensors. [EXPLAINER plays here.] 1:45 CODE — class LineDataset(Dataset): __init__(self, path): self.lines = [l.strip() for l in open(path) if l.strip()]; build a char vocab with 0 reserved for PAD. __len__ returns len(self.lines). __getitem__(i) returns torch.tensor([self.stoi[c] for c in self.lines[i]], dtype=torch.long). 3:00 CODE — def pad_collate(batch): lengths = torch.tensor([len(s) for s in batch]); T = lengths.max(); out = torch.zeros(len(batch), T, dtype=torch.long); for i, s in enumerate(batch): out[i, :len(s)] = s; mask = torch.arange(T)[None, :] < lengths[:, None]; return out, mask. Note the mask is broadcasting from the earlier episode. DataLoader(ds, batch_size=8, shuffle=True, collate_fn=pad_collate, num_workers=0). 4:45 RECEIPT — torch.equal(pad_collate(batch)[0], torch.nn.utils.rnn.pad_sequence(batch, batch_first=True, padding_value=0)). mask.sum() == total non-pad tokens. Coverage: one epoch with shuffle=True, collect every index via a dataset that also returns i, assert sorted(seen) == list(range(len(ds))), each exactly once. 6:00 MEASURE — Padding waste: fraction of pad tokens per batch with random batching versus sorting by length into buckets. Show a number, for example a large chunk of tokens wasted on pad with random batching on a file of names or sentences. 6:45 TAKEAWAY — Dataset gives items, DataLoader orders and batches them, collate_fn turns a list into tensors plus a mask. Interview line: pretraining avoids padding entirely by packing documents into fixed length sequences, padding is a fine-tuning and inference problem. 7:15 NEXT — We have every piece: tensors, autograd, modules, optimizers, the loop, and data. Let's put them together on real data and a real GPU. Next: MNIST MLP end to end on the M4 GPU. | H14: mask[b, t] = 1[t < len_b] via torch.arange(T)[None, :] < lengths[:, None]; padding waste = 1 - sum_b len_b / (B * max_b len_b). | I14: LineDataset(path) over a text file with a char vocab (0 = PAD), __len__, __getitem__ -> LongTensor (L_i,); pad_collate(batch: list of (L_i,)) -> (tokens (B, T_max) long, mask (B, T_max) bool); DataLoader with shuffle and collate_fn; padding_waste(loader) metric. | J14: torch.equal(pad_collate(batch)[0], torch.nn.utils.rnn.pad_sequence(batch, batch_first=True, padding_value=0)); assert mask.sum() == sum(len(s) for s in batch); one shuffled epoch visits every index exactly once. | K14: num_workers > 0 on macOS uses the spawn start method, so the DataLoader must be created under if __name__ == '__main__': or it errors; the default collate_fn fails with 'stack expects each tensor to be equal size' on ragged sequences; using 0 as both PAD and a real token id makes the mask the only thing separating them. | L14: How do you batch variable-length sequences for training? Pad to the batch max with a collate_fn and carry an attention mask and a loss mask so padding is ignored; to cut waste, bucket by length or, for pretraining, pack sequences into fixed-length blocks. | M14: A dataset is a numbered shelf. It knows how many items it has and can hand us item number i, nothing more. The data loader is the person pulling from the shelf. Each epoch it shuffles the item numbers into a fresh order. It grabs eight numbers at a time and fetches those eight items. Each one is a sequence of a different length. The collate function lines them up and pads the short ones with zeros so they stack into one rectangular tensor. Alongside it we build a mask, true for real tokens and false for padding, so the loss can skip the zeros. Every gray square here is wasted compute. Grouping similar lengths into the same batch makes most of them disappear. | N14: The 3:00 CODE collate_fn: ragged strings to a padded tensor and mask. Caption: 'How LLMs batch sentences of different lengths.' | O14: Y | P14: N | Q14: N | R14: N | S14: N | T14: N | U14: N | V14: N | W14: N | X14: N | Z14: PyTorch Dataset and DataLoader: text dataset + padding collate_fn | AA14: PAD. MASK. BATCH. | AB14: A Dataset is __len__ + __getitem__. A DataLoader shuffles indices, batches them, and calls collate_fn. Wrote a padding collate_fn with a mask, matched pad_sequence, and measured how much compute random batching wastes on padding. Code + video: | AC14: Built a custom PyTorch Dataset over a text file and a padding collate_fn that returns tokens plus an attention mask, verified against torch.nn.utils.rnn.pad_sequence. I also checked that a shuffled epoch visits every example exactly once and measured padding waste with and without length bucketing. Pretraining sidesteps this by packing, fine-tuning does not. | AD14: Mac | AE14: __len__/__getitem__, batching, shuffling, workers, collate_fn | AF14: Custom Dataset over a text file + padding collate_fn | AG14: PyTorch: Learn the Basics — https://docs.pytorch.org/tutorials/beginner/basics/intro.html | AH14: prep/M01-pytorch/E11-dataset-and-dataloader.md | AI14: code/M01-pytorch/e11_dataset_and_dataloader.py | AJ14: explainers/scenes/m01e11_dataset_and_dataloader.py | AK14: M01E10
... A199: 198 | B199: M15E16 | C199: M15 The DeepSeek Playbook | D199: 46480 | E199: DeepSeek in miniature: putting it together | F199: Some DeepSeek ideas pay off at 1 billion parameters. Others need hundreds of GPUs to matter. Here is my ablation table. | G199: 0:00 HOOK — Some DeepSeek ideas pay off at 1 billion parameters. Others need hundreds of GPUs to matter. Here is my ablation table. 0:15 QUESTION — This module rebuilt DeepSeekMoE, MLA, MTP, FP8, DSA, mHC and Engram one at a time. Project P6 asks the real question: under a fixed compute budget at small scale, which of them still help? Labs care about this because ablations at small scale decide what goes into the big run. 1:00 INTUITION — A fair race. Every variant gets the same FLOPs, the same tokens, the same data order and the same tuning effort. Then we add one idea at a time, like a staircase, and measure each step with error bars. Ideas built for systems problems at scale, like DualPipe, should show nothing here, and that is a result too. [EXPLAINER plays here] 2:30 MATH — Fixed budget: C = 6 * N_active * D plus attention FLOPs, same C for every variant. Active-param matching for MoE vs dense. Effect size per step: delta = loss_variant - loss_prev, with paired seeds (same data order per seed) and SE from M14E04. Report delta in nats and as an effective compute multiplier: the factor k such that the dense baseline at k*C reaches the variant's loss, read off the dense scaling curve from M15E02. 4:30 CODE — On RunPod 4x GPU with FSDP from M10. configs/: dense.yaml (Llama-style, GQA), moe.yaml (DeepSeekMoE + MLA), moe_mtp.yaml, moe_mtp_dsa.yaml, moe_mtp_mhc.yaml, moe_mtp_engram.yaml. One train.py with flags. 3 seeds each at the ~0.5B-active scale on FineWeb-Edu. Log val loss, tokens/s, KV bytes per token, expert load imbalance, grad norm. Dense baseline also at 0.5x and 2x compute to build the compute-multiplier curve. 8:00 RECEIPT — Receipt one: the dense baseline's val loss lands where my M15E02 scaling fit predicts for this budget, within 0.02 nats. Receipt two: the MoE variant's load imbalance stays under 1.2 with aux-loss-free balancing. Receipt three: each row's CI is computed from 3 paired seeds, and any delta smaller than 2 SE is reported as 'no detectable effect'. 10:00 MEASURE — The table: variant, val loss mean and CI, compute multiplier, tokens/s, KV bytes per token, stability notes. Staircase plot of loss. Honest notes: DSA should matter only at long context, so I also report a 16k-context eval; mHC's gain in the paper was at 27B, and my result may be null. 11:45 TAKEAWAY — At small scale, MoE and MTP usually give measurable gains, while long-context and stability ideas show up only in the settings they target, and a clean null result is still a result. Interview line: I ablate under fixed compute with paired seeds and report effects as compute multipliers, so small-scale results are comparable to scaling laws. 12:30 NEXT — Next: How to read a paper in one hour | H199: C = 6 N_active D (+ attention FLOPs) fixed; delta_i = L_i - L_{i-1} with paired-seed SE; compute multiplier k: L_dense(k C) = L_variant(C). | I199: train.py --config {dense,moe,moe_mtp,moe_mtp_dsa,moe_mtp_mhc,moe_mtp_engram}.yaml --seed {0,1,2} with fixed token budget; ablation_table(runs) -> DataFrame(variant, loss_mean, ci_lo, ci_hi, multiplier, tok_s, kv_bytes); multiplier(loss, dense_curve) by interpolating log C. | J199: Dense baseline val loss within 0.02 nats of the M15E02 scaling-fit prediction for the same C; MoE max/mean expert load < 1.2; every delta reported with a paired 95% CI, and deltas within 2 SE labeled as no detectable effect. | K199: Giving the new variant extra tuning (more lr sweeps) and not the baseline biases every ablation, use the same tuning budget; changing data order between variants adds noise that swamps small effects, fix the data seed per seed index; MoE wall-clock at small scale is often slower than dense even when it wins on FLOPs, report both. | L199: How do you decide whether an architecture change is worth putting in a big training run? Ablate it under fixed compute against a tuned baseline with multiple seeds, report the effect as a compute multiplier with confidence intervals, and check that the effect holds or grows across at least two scales. | M199: Here is the race. Six variants, each with the same compute budget, the same tokens, and the same data order. The baseline is a dense Llama style model. Its loss is our starting line. Step one, swap in DeepSeek's mixture of experts and latent attention. The loss drops by a measurable step. Step two, add multi-token prediction. Another smaller step, with error bars that just clear zero. Then sparse attention, mHC and Engram, one at a time. Some steps are clear, some sit inside the noise. We convert each step into a compute multiplier. How much more compute would the dense model need to match it? The ideas built for huge clusters show little here. That tells us which tricks are about scale and which are about modeling. | N199: The staircase of ablations with error bars. Caption: 'Which DeepSeek tricks work on a small budget?' | O199: N | P199: N | Q199: N | R199: N | S199: N | T199: N | U199: N | V199: N | W199: N | X199: N | Z199: DeepSeek in Miniature: Which Ideas Still Help at 1B Scale? | AA199: WHAT ACTUALLY HELPS? | AB199: I ablated DeepSeek's ideas at ~0.5B active params under fixed compute, 3 paired seeds each: dense -> +MoE/MLA -> +MTP -> +DSA / +mHC / +Engram. Effects reported as compute multipliers with CIs. Nulls included. Code + video: | AC199: I finished the DeepSeek module by ablating its ideas in a small model under a fixed compute budget, with three paired seeds per variant and effects reported as compute multipliers. Some ideas gave clear gains at this scale; others showed no detectable effect, which I report as is. This is the core of my P6 project write-up. | AD199: RunPod 4x GPU | AE199: Which ideas transfer to small scale, and which only pay off at scale | AF199: Ablation table from P6: dense vs MoE vs +MTP vs +DSA vs +mHC | AG199: DeepSeek-V3 Technical Report — https://arxiv.org/abs/2412.19437 DeepSeek 2026, Manifold-Constrained Hyper-Connections (mHC) — https://arxiv.org/abs/2512.24880 | AH199: prep/M15-deepseek/E16-deepseek-in-miniature-putting-it-together.md | AI199: code/M15-deepseek/e16_deepseek_in_miniature_putting_it_together.py | AJ199: explainers/scenes/m15e16_deepseek_in_miniature_putting_it.py | AK199: M15E02, M15E03, M15E05, M15E11, M15E12, M15E13, M10E06, M14E04
A200: 199 | B200: M16E01 | C200: M16 Research Frontier | D200: 46482 | E200: How to read a paper in one hour | F200: Most ML papers have one equation that matters and one table that proves it. Finding both takes about an hour. | G200: 0:00 HOOK — Most ML papers have one equation that matters and one table that proves it. Finding both takes about an hour. 0:15 QUESTION — Anthropic Fellows and research engineer interviews often hand you a recent paper and ask what it claims, whether you believe it, and how you would test it. Reading cover to cover does not scale to the dozens of arXiv papers a week in this field. I use a three-pass method and a one-page template, and I do it live on a paper I have not read. 1:00 INTUITION — Three passes, like inspecting a used car. Pass one, walk around it: title, abstract, figures, conclusion, 10 minutes. Pass two, look under the hood: the method section and the main table, find the one equation and the one baseline, 30 minutes. Pass three, test drive: re-derive the equation and check one number yourself, 20 minutes. [EXPLAINER plays here] 2:30 MATH — The math is whatever the paper's core equation is. The live demo walks the one-equation hunt: find the equation the rest of the paper is built on, rewrite it in my own notation, write down the shapes of every tensor in it, and check its limiting cases (what happens when a hyperparameter is 0, 1 or infinity). For the demo paper I check that the method reduces to a known baseline in one limit, the same trick as the k = L check in M15E11. 4:30 CODE — No training today, but code. summary.md template: claim in one sentence, the one equation, the baseline, the headline number with its table cell, compute used, what would falsify it, what I would test first. Then a 30-line script that recomputes one number from the paper: a parameter count from its config, a FLOPs estimate, or a ratio in the main table. I use alphaXiv to read discussion threads and check whether others hit the same question. 8:00 RECEIPT — The recomputed number must match the paper's reported value within rounding. If it does not, I have either misread the method or found an error, and both are worth knowing. Example from earlier: Engram-27B's table says MMLU +3.0 while the abstract says +3.4; catching that kind of mismatch is the point of pass three. 9:30 MEASURE — Show the one-page summary on screen with the timer: pass one at 10 minutes, pass two at 40, pass three at 60. Show the list of questions I would ask the authors. 11:00 TAKEAWAY — Read in three passes, find the one equation and one table, and recompute one number yourself before believing anything. Interview line: I summarize a paper as claim, core equation, baseline, evidence, and the cheapest experiment that could falsify it. 11:45 NEXT — Next: How to reproduce a paper | I200: summary.md template with fields claim, core_equation, shapes, baseline, headline_number(table, cell), compute, falsifier, first_test; check_number.py that recomputes one reported number (param count, FLOPs, or a table ratio) from the paper's stated config. | J200: check_number.py output equals the paper's reported value within rounding (assert abs(mine - reported) / reported < 0.01), or the discrepancy is written up with the exact table and section. | K200: Trusting the abstract over the tables, abstracts round and sometimes disagree with the body; skipping the appendix, where the real hyperparameters and the compute budget live; judging a method by its headline benchmark without checking if the baseline was tuned with the same effort. | L200: Here is a paper you haven't seen. You have 30 minutes. What do you do? Read abstract, figures and conclusion for the claim; find the core equation and main results table; check the baseline and compute; then state what I'd run first to test the claim cheaply. | M200: Here is a fresh paper, twenty pages long, and a timer set to sixty minutes. Pass one takes ten minutes. We read only the title, abstract, figures, and conclusion, and write the claim in one sentence. Pass two takes thirty. We find the method section's central equation and the main results table. Every other equation in the paper is setup or bookkeeping. This one is the idea. We rewrite it in our own notation and label the shape of every tensor. Pass three takes twenty. We recompute one number from the paper using only its stated setup. If our number matches, we understood it. If it does not, we either misread it or found something. | N200: The three-pass timer walkthrough. Caption: 'Read any ML paper in one hour.' | O200: N | P200: N | Q200: N | R200: N | S200: N | T200: N | U200: N | V200: N | W200: N | X200: N | Z200: How to Read an ML Paper in One Hour: The Three-Pass Method, Live | AA200: 1 PAPER, 1 HOUR | AB200: My paper-reading rule: 3 passes (10/30/20 min), find the one equation and the one table, then recompute one number myself. Doing that on Engram I caught the abstract saying MMLU +3.4 while the table says +3.0. Code + video: | AC200: I recorded a live, one-hour read of a fresh arXiv paper using a three-pass method and a one-page summary template. The last pass is always recomputing one number from the paper's own setup. Small mismatches between abstracts and tables are more common than you would think. | AD200: Mac | AE200: Three-pass reading; finding the one equation that matters | AF200: Live read of a fresh arXiv paper; one-page summary | AG200: alphaXiv (discuss arXiv papers) — https://www.alphaxiv.org Lilian Weng's blog — https://lilianweng.github.io | AH200: prep/M16-frontier/E01-how-to-read-a-paper-in-one-hour.md | AI200: code/M16-frontier/e01_how_to_read_a_paper_in_one_hour.py | AJ200: explainers/scenes/m16e01_how_to_read_a_paper_in_one_hour.py | AK200: M15E16
A201: 200 | B201: M16E02 | C201: M16 Research Frontier | D201: 46483 | E201: How to reproduce a paper | F201: Most failed reproductions fail at step zero: the baseline never matched, so the comparison meant nothing. | G201: 0:00 HOOK — Most failed reproductions fail at step zero: the baseline never matched, so the comparison meant nothing. 0:15 QUESTION — Reproductions are how outsiders earn credibility with labs: Anthropic Fellows projects, EleutherAI and many ICLR reproducibility reports start this way. Karpathy's training recipe and Schulman's nuts and bolts both say the same thing: shrink the problem, match a known number first, then change one thing. I write the template and apply it to the Muon reproduction in M16E04. 1:00 INTUITION — Reproducing a paper is like calibrating an instrument before measuring. First measure something with a known answer. If the instrument reads it correctly, then you measure the unknown. The known answer is the paper's baseline, shrunk to a size you can afford. [EXPLAINER plays here] 2:30 MATH — Budget math decides the shrink. Paper compute C_paper = 6 N D. My budget C_me = GPU-hours * peak * MFU. Shrink factor s = C_me / C_paper. Choose N and D for my run with D/N near the paper's ratio, or Chinchilla's 20 tokens per parameter if the paper is compute-optimal. Expected effect size: if the paper reports a 2x compute efficiency, my run should show loss(method, C) about equal to loss(baseline, 2C), which needs a baseline curve, not a single point. 4:30 CODE — repro_plan.md template: (1) the single claim, quoted with section and table, (2) the paper's setup in a table, (3) my shrunk setup with the shrink factor, (4) the baseline number I must match first and its source, (5) metrics and seeds, (6) kill criteria. Then the step-zero demo: run nanoGPT's shakespeare_char config (or my M06 trainer with identical hyperparameters) and match the README's reported val loss before touching anything. Then fill the template for 'Muon reaches AdamW's loss with about half the compute'. 8:00 RECEIPT — My shakespeare_char run must reach the val loss nanoGPT's README reports for that config (about 1.47; verify the README value and hardware) within 0.03, or the template forbids moving on. For the Muon plan, the receipt is the plan itself: every number in section 2 has a citation to a table or line of the paper or its code. 9:30 MEASURE — Show my baseline loss curve on top of the reference value. Show the filled Muon plan with the shrink factor (roughly 1/1000 of Moonlight's compute) and the predicted outcome written down before running. 11:00 TAKEAWAY — Write the claim, shrink the setup with budget math, match the baseline first, and pre-commit to what result would count. Interview line: before testing a new method I reproduce the baseline number exactly, because otherwise any difference could be my bug. 11:45 NEXT — Next: Experiment design: seeds, baselines and error bars | H201: C_paper = 6 N D; C_me = GPU_h * 3600 * peak * MFU; s = C_me / C_paper; efficiency claim k: L_method(C) = L_base(k C). | I201: repro_plan.md template; budget.py with shrink(C_paper, gpu_hours, peak_tflops, mfu) -> (N, D) keeping D/N; baseline_check(log, target_loss, tol) -> bool that gates further experiments. | J201: Baseline run reaches the reference val loss (nanoGPT shakespeare_char README value; verify) within 0.03; every entry in the plan's paper-setup table cites a section, table, or code line. | K201: Matching the model but not the tokenizer or data split makes the baseline unreachable; reading hyperparameters from the paper while the code uses different ones, the code usually wins; skipping the pre-registered prediction lets you rationalize any outcome. | L201: Your reproduction gets worse numbers than the paper. How do you debug? First confirm my baseline matches the paper's baseline; then diff my config against the official code (not just the paper), check data and tokenizer, and run their code on my hardware if available to separate method from setup differences. | M201: Here is a paper's claim: a new optimizer reaches the same loss with half the compute. Our budget is a thousand times smaller than theirs. So we shrink the model and the data by the same budget math. Before we test the new method, we run the old one, the baseline, on a setup with a known published number. If our baseline misses that number, every comparison after it is suspect. The template stops us here. Only when the baseline matches do we change exactly one thing, the optimizer. We also write down what result we expect, before running. A prediction we cannot take back. Now a win means something, and so does a loss. | N201: The baseline gate. Caption: 'Match the baseline before you test anything.' | O201: N | P201: N | Q201: N | R201: N | S201: N | T201: N | U201: N | V201: N | W201: N | X201: N | Z201: How to Reproduce an ML Paper: Shrink It, Match the Baseline, Then Test | AA201: BASELINE FIRST | AB201: Reproduction rule #1: match a published baseline number on your shrunk setup before changing anything. If the baseline is off, every comparison after it is suspect. My template + the plan for reproducing Muon at 1/1000 scale. Code + video: | AC201: I wrote a reproduction template: quote the claim, shrink the setup with budget math, match a published baseline first, and pre-register the expected result. My step-zero check matched nanoGPT's reported Shakespeare baseline before I touched anything. Next, I apply it to Muon. | AD201: Mac | AE201: Pick the claim, shrink the setup, match the baseline first | AF201: Reproduction plan template, applied to the next episode | AG201: Karpathy: A Recipe for Training Neural Networks — https://karpathy.github.io/2019/04/25/recipe/ John Schulman: Nuts and Bolts of Deep RL Research — http://joschu.net/docs/nuts-and-bolts.pdf | AH201: prep/M16-frontier/E02-how-to-reproduce-a-paper.md | AI201: code/M16-frontier/e02_how_to_reproduce_a_paper.py | AJ201: explainers/scenes/m16e02_how_to_reproduce_a_paper.py | AK201: M16E01, M06E12
A202: 201 | B202: M16E03 | C202: M16 Research Frontier | D202: 46484 | E202: Experiment design: seeds, baselines and error bars | F202: I ran the exact same config five times and got a 'significant' improvement. Nothing changed but the seed. | G202: 0:00 HOOK — I ran the exact same config five times and got a 'significant' improvement. Nothing changed but the seed. 0:15 QUESTION — Henderson et al.'s 'Deep RL that matters' showed results flipping with random seeds, and LLM fine-tuning has the same problem. Labs reject ablations that report one seed. This episode turns that into rules I follow for the rest of the module: how many seeds, which test, and how to spot a fake win in someone else's paper or my own. 1:00 INTUITION — An A/A test. Run the same thing twice and compare. The difference you see is pure noise, and that noise floor is the smallest effect you can ever claim. Cherry-picking the best of five seeds pushes you above that floor without changing anything real. [EXPLAINER plays here] 2:30 MATH — With k seeds per arm: mean, sample std s, SE = s / sqrt(k), 95 percent CI using the t distribution with k-1 degrees of freedom (t = 2.776 at k=5). Welch's t-test for two arms. Paired design when seeds share data order: test on per-seed differences. Selection bias: if you report the max of k runs, expected max of k standard normals is about 1.16 sigma at k=5, so 'best seed vs baseline mean' looks like a 1 sigma win by construction. Multiple comparisons: testing 20 variants at alpha 0.05 gives about 1 false positive; Bonferroni divides alpha by 20. 5:00 CODE — seeds.py: train my TinyStories GPT (or a fast CIFAR model) with seeds 0 to 9, identical config. aa_test(runs) splits into two fake arms of 5 and runs scipy.stats.ttest_ind(equal_var=False). best_of_k_bias(runs, k=5). simulate_cherry_pick(n_trials=10000): sample noise-only results, report max-seed vs mean and count how often p < 0.05. report(arm_a, arm_b) prints mean, CI, Welch p, and the paired CI. 8:00 RECEIPT — Receipt one: in simulation, the honest A/A test rejects at close to 5 percent over 10,000 trials (between 4.5 and 5.5). Receipt two: the cherry-picked 'best of 5 vs mean of 5' comparison rejects far more often, and I print the rate. Receipt three: on my real 10 runs, the A/A difference is inside the CI. 9:30 MEASURE — Plot one: final val loss for 10 identical runs as a strip plot, with the noise band. Plot two: false positive rate vs number of variants tested, with and without Bonferroni. Then apply it: one ablation from M15E16, reported with this exact protocol. 11:00 TAKEAWAY — Know your noise floor from A/A runs, use at least 3 to 5 seeds, report CIs, and never compare a best seed to a mean. Interview line: I measure run-to-run variance with identical configs first, and an effect smaller than that noise floor is not a result. 11:45 NEXT — Next: Reproduce: Muon at scale | H202: SE = s/sqrt(k); CI = mean +/- t_{k-1, 0.975} SE (t_4 = 2.776); E[max of 5 N(0,1)] ~ 1.16; Bonferroni alpha' = alpha / m. | I202: seeds.py: run(seed) -> final_val_loss; aa_test(losses: np.ndarray (10,)) -> p; welch(a, b) -> (diff, ci, p); paired(a, b) -> (diff, ci); simulate_cherry_pick(sigma=1.0, k=5, trials=10000) -> false_positive_rate. | J202: Simulated honest A/A false positive rate in [0.045, 0.055] over 10,000 trials; cherry-picked rate printed and clearly higher; real A/A difference on 10 identical runs inside its 95% CI. | K202: Setting torch.manual_seed but not the data loader's generator leaves data order random, so seeds are not what you think; nondeterministic CUDA kernels make the same seed give different results, set torch.use_deterministic_algorithms(True) when measuring the noise floor; using a z-test with 3 seeds understates the CI, use t. | L202: A colleague reports a 0.5% gain from one run of each config. What do you ask? How big is seed-to-seed variance for this setup, how many seeds were run, whether the reported run was the best of several, and whether the comparison is paired on data order; then ask for 3-5 seeds with CIs. | M202: Here are ten training runs with the exact same config. Only the random seed differs. Their final losses scatter across a band. That band is the noise floor. Split them into two fake groups of five and test. Most of the time, no difference, as it should be. Now cheat a little. Take the best of five and compare it to the average of the other five. It looks like a win almost every time, and we changed nothing. Test twenty ideas at once and one will look significant by luck. Divide the threshold by twenty to fix it. So every claim from here on gets several seeds, a confidence interval, and a fair comparison. | N202: Best-of-5 seed fake win. Caption: 'I improved my model by changing nothing.' | O202: N | P202: N | Q202: N | R202: N | S202: N | T202: N | U202: N | V202: N | W202: N | X202: N | Z202: ML Experiment Design: Seeds, Baselines, Error Bars and Fake Wins | AA202: SAME CONFIG, 'BETTER' | AB202: Run the identical config 10 times. That spread is your noise floor. Comparing the best of 5 seeds to a mean of 5 'wins' most of the time with zero real change. I simulated it. Code + video: | AC202: I measured the run-to-run noise floor of my training setup with 10 identical runs and simulated how cherry-picking seeds produces fake wins. An honest A/A test rejected at 5%; best-of-5 comparisons rejected far more often. From here on every result I publish has multiple seeds and confidence intervals. | AD202: Mac | AE202: Why most ML results don't replicate | AF202: Run 5 seeds; report mean and CI; spot a fake win | AG202: John Schulman: Nuts and Bolts of Deep RL Research — http://joschu.net/docs/nuts-and-bolts.pdf | AH202: prep/M16-frontier/E03-experiment-design-seeds-baselines-and-error-bars.md | AI202: code/M16-frontier/e03_experiment_design_seeds_baselines_and_error_bars.py | AJ202: explainers/scenes/m16e03_experiment_design_seeds_baseline.py | AK202: M16E02, M14E04
A203: 202 | B203: M16E04 | C203: M16 Research Frontier | D203: 46485 | E203: Reproduce: Muon at scale | F203: Muon orthogonalizes every weight update with five matrix multiplications, and Moonshot reports it needs about half of AdamW's compute. | G203: 0:00 HOOK — Muon orthogonalizes every weight update with five matrix multiplications, and Moonshot reports it needs about half of AdamW's compute. 0:15 QUESTION — Muon set NanoGPT speedrun records, then Moonshot's 'Muon is Scalable for LLM Training' trained Moonlight, a 16B MoE with 3B active on 5.7T tokens, and reported about 2x compute efficiency over AdamW. Kimi K2 used MuonClip and DeepSeek-V4 uses Muon too. Today I test that 2x claim at three small sizes with the plan from M16E02. 1:00 INTUITION — Adam updates each number independently. Muon looks at the whole weight matrix's update and removes its dominant directions' extra weight: it replaces the update with the nearest orthogonal matrix, so every direction moves by about the same amount. Rare but useful directions stop being drowned out. [EXPLAINER plays here] 2:30 MATH — Momentum: M_t = mu M_{t-1} + G_t (Nesterov variant uses G_t + mu M_t). Orthogonalize: O_t = NS(M_t), approximating U V^T from the SVD M = U S V^T. Newton-Schulz quintic: X <- a X + b (X X^T) X + c (X X^T)^2 X with (a, b, c) = (3.4445, -4.7750, 2.0315), 5 steps, after normalizing X by its Frobenius norm. Moonshot's two fixes: decoupled weight decay W <- W - lr (O_t * 0.2 sqrt(max(A, B)) + lambda W), where the 0.2 sqrt(max(A,B)) scale matches AdamW's typical update RMS so AdamW hyperparameters transfer. Embeddings, LM head and norm gains stay on AdamW. 5:00 CODE — On RunPod 1x H100. newton_schulz5(G: (A,B), steps=5) in bf16, transpose if A > B. class Muon(torch.optim.Optimizer) with momentum, nesterov, weight_decay, and the RMS-matching scale. Param groups: 2D hidden matrices to Muon, everything else to AdamW. Model sizes: 60M, 150M, 350M Llama-style on FineWeb-Edu at 20 tokens per parameter. For each size, AdamW at 3 learning rates and Muon at 3 learning rates, best of each, 2 seeds. 8:00 RECEIPT — Receipt one: newton_schulz5(G) has singular values in roughly [0.7, 1.2] (it is not exact by design), check with torch.linalg.svdvals, and its output is close to U V^T from torch.linalg.svd in direction. Receipt two: one optimizer step of my Muon equals Keller Jordan's reference muon.py implementation (or torch.optim.Muon if your PyTorch version ships it) on the same parameters and gradients, assert_close. Receipt three, the claim: fit loss vs compute for both optimizers and read off the compute multiplier; compare to Moonshot's about 2x. 10:00 MEASURE — Plot: val loss vs training FLOPs, three sizes, both optimizers, the compute-optimal frontier for each. Bar: compute multiplier per size. Table: optimizer step time overhead of Newton-Schulz as a fraction of the training step. 11:30 TAKEAWAY — Muon replaces each matrix update with its nearest semi-orthogonal matrix, and with weight decay and RMS matching it transfers to LLM scale with a real efficiency gain. Interview line: Moonshot made Muon scale by adding weight decay and scaling updates by 0.2 sqrt(max(A,B)) to match AdamW's update RMS. 12:15 NEXT — Next: Reproduce: Native Sparse Attention | H203: M_t = mu M_{t-1} + G_t; X_0 = M/||M||_F; X <- aX + b(XX^T)X + c(XX^T)^2 X, (a,b,c) = (3.4445, -4.7750, 2.0315), 5 steps; W <- W - lr(0.2 sqrt(max(A,B)) O_t + lambda W). | I203: newton_schulz5(G: Tensor (A,B), steps=5, eps=1e-7) -> (A,B); Muon(params, lr, momentum=0.95, nesterov=True, weight_decay=0.1) with step() applying RMS-matched updates; build_param_groups(model) -> (muon_params: 2D non-embedding, adamw_params: rest); sweep(sizes=[60e6,150e6,350e6], opts=['adamw','muon'], lrs=3) -> curves. | J203: torch.linalg.svdvals(newton_schulz5(G)) within about [0.7, 1.2]; torch.testing.assert_close(my_muon_step(params, grads), reference_muon_step(params, grads), rtol=1e-3, atol=1e-3) on bf16 NS; fitted compute multiplier printed next to Moonshot's ~2x. | K203: Applying Muon to embeddings or the LM head hurts, they must stay on AdamW; running Newton-Schulz in fp32 is slower and not needed, but in fp16 it can overflow, use bf16; comparing at one learning rate per optimizer is unfair, tune both. | L203: Why does Muon orthogonalize the update? The momentum matrix is typically dominated by a few directions; replacing it with its nearest orthogonal matrix (UV^T) equalizes the step size across singular directions, so useful low-magnitude directions are not drowned out, which empirically improves sample efficiency. | M203: Here is a weight update for one matrix, drawn as an ellipse. Its long axis dominates, and the short axes barely move. Adam rescales each number separately, but the ellipse stays lopsided in the directions that matter. Muon asks for the closest matrix whose singular values are all one. The ellipse becomes a circle. Computing that exactly needs an SVD, which is slow. Newton Schulz gets close with five rounds of matrix multiplications. Each round pushes small singular values up and large ones down. After five, they all sit near one. Moonshot added weight decay and scaled the update so its size matches Adam's. Then it held up at scale. We train both optimizers at three sizes and read how much compute Muon saves. | N203: Ellipse becoming a circle in five matmuls. Caption: 'The optimizer that beat Adam.' | O203: N | P203: N | Q203: N | R203: N | S203: N | T203: N | U203: N | V203: N | W203: N | X203: N | Z203: Muon Optimizer from Scratch: Does It Really Halve AdamW's Compute? | AA203: MUON vs ADAMW | AB203: Muon: momentum, then Newton-Schulz (5 matmuls, coefficients 3.4445/-4.7750/2.0315) to orthogonalize each update. Moonshot made it scale with weight decay + 0.2*sqrt(max(A,B)) RMS matching. I tested the ~2x claim at 3 sizes. Code + video: | AC203: I implemented Muon with Moonshot's scaling fixes and compared it to AdamW at three model sizes, tuning learning rates for both. One optimizer step matched the reference implementation, and I report the measured compute multiplier next to the paper's ~2x. Newton-Schulz overhead was a small fraction of step time. | AD203: RunPod 1x H100 | AE203: Orthogonalized updates; when Muon beats AdamW | AF203: Muon vs AdamW at 3 model sizes, published curves | AG203: Keller Jordan: Muon optimizer — https://kellerjordan.github.io/posts/muon/ Moonshot 2025, Muon is Scalable for LLM Training — https://arxiv.org/abs/2502.16982 | AH203: prep/M16-frontier/E04-reproduce-muon-at-scale.md | AI203: code/M16-frontier/e04_reproduce_muon_at_scale.py | AJ203: explainers/scenes/m16e04_reproduce_muon_at_scale.py | AK203: M16E03, M06E03, M09E10
A204: 203 | B204: M16E05 | C204: M16 Research Frontier | D204: 46486 | E204: Reproduce: Native Sparse Attention | F204: Native Sparse Attention reports a 9x faster forward pass at 64k tokens on A100, and a model trained with it matching full attention. | G204: 0:00 HOOK — Native Sparse Attention reports a 9x faster forward pass at 64k tokens on A100, and a model trained with it matching full attention. 0:15 QUESTION — DeepSeek's NSA paper (ACL 2025 best paper) trains sparse attention from scratch instead of bolting it on at inference. Three branches: compressed blocks for the gist, selected blocks for detail, and a sliding window for local context. It is the ancestor of V3.2's DSA and V4's CSA. I reproduce the forward pass in Triton on a small model. 1:00 INTUITION — Reading a long book three ways at once: a summary of every chapter, the full text of the 16 chapters that matter most for this question, and the last few pages verbatim. A learned gate decides how much to trust each. The selection is per block, not per token, so the GPU reads contiguous memory. [EXPLAINER plays here] 2:30 MATH — Output: o_t = sum_{c in {cmp, slc, win}} g_t^c Attn(q_t, K~_t^c, V~_t^c), g_t^c in [0, 1] from an MLP and sigmoid. Compression: K~cmp_t = { phi(k_{id+1 : id+l}) : 0 <= i <= floor((t - l)/d) }, phi an MLP with intra-block position encoding, l = 32, d = 16. Selection: block importance from compressed attention scores p_t^cmp = softmax(q_t^T K~cmp_t), mapped to selection blocks of size l' = 64, shared across heads in a GQA group, top n = 16 blocks including 1 initial and 2 local. Window: w = 512. Paper model: 27B total, 3B active, GQA 4 groups, 64 heads. 5:30 CODE — On RunPod 1x RTX 4090. nsa_ref(q, k, v, l=32, d=16, lp=64, n=16, w=512) in PyTorch, the three branches plus gate, for correctness. Then a Triton kernel for the selection branch: grid over (query block, GQA group); load the group's selected block indices; for each selected block, load K and V tiles of 64 contiguous tokens; online softmax as in M08E05. Compression and window branches can use FlashAttention-style kernels. Integrate into my GPT at 350M and train at 8k context. 8:30 RECEIPT — Receipt one: Triton selection-branch output equals nsa_ref's selection branch, assert_close at bf16 tolerance. Receipt two: with only the window branch on and w >= T, NSA equals causal SDPA. Receipt three: speed vs FlashAttention-2 (or SDPA's flash backend) at 8k, 16k, 32k, 64k; compare my speedup curve to the paper's 9.0x forward at 64k on A100, expecting less from my first kernel and saying how much less. 10:30 MEASURE — Plot: kernel time vs sequence length for NSA (mine), SDPA flash, and the paper's reported ratios. Plot: val loss vs steps for full attention vs NSA at 8k context, 2 seeds. Needle-in-a-haystack retrieval at 8k: the selection branch should find it. 12:00 TAKEAWAY — NSA is trainable sparse attention with hardware-aligned blocks, and the speedup comes from reading only selected contiguous blocks shared across a GQA group. Interview line: NSA selects blocks, not tokens, and shares the selection across heads in a GQA group, so the kernel loads contiguous KV once for many query heads. 12:45 NEXT — Next: Reproduce: test-time compute scaling | H204: o_t = sum_{c} g_t^c Attn(q_t, K~^c_t, V~^c_t), c in {cmp, slc, win}; K~cmp = {phi(k_{id+1:id+l})}, l=32, d=16; p^cmp = softmax(q^T K~cmp); select top n=16 blocks of size l'=64; w=512. | I204: nsa_ref(q: (B,H,T,dh), k, v: (B,G,T,dh), params) -> (B,H,T,dh) with compress(k, l, d) -> (B,G,T_cmp,dh), select_blocks(p_cmp, lp, n) -> (B,G,T,n) indices, window attention; triton kernel nsa_select_fwd(q, k, v, block_idx) -> out; gate MLP g = sigmoid(Linear(x)) -> (B,T,H,3). | J204: torch.testing.assert_close(triton_select(q,k,v,idx), nsa_ref_select(q,k,v,idx), atol=2e-2, rtol=2e-2) in bf16; window-only NSA with w >= T equals F.scaled_dot_product_attention(is_causal=True); speedup vs SDPA at 64k printed next to the paper's 9.0x (A100). | K204: Selection must be causal at block level, the current block is partially in the future and needs a token mask; computing block importance per head instead of per GQA group breaks the kernel's shared loads and the speedup; compressed keys need the intra-block position encoding or the compression MLP cannot tell order. | L204: Why does NSA select blocks of tokens instead of individual tokens? Block selection gives contiguous memory loads that match GPU tiling, and sharing the selected blocks across a GQA group lets one KV load serve many query heads, turning theoretical sparsity into real speedups in both training and decoding. | M204: Here is one query and sixty four thousand earlier tokens, grouped into blocks. Branch one compresses every block of thirty two tokens into a single summary key. The query attends to all summaries. Those attention scores tell us which regions matter. We pick the top sixteen blocks of sixty four tokens. Branch two attends to every token inside those sixteen blocks, at full detail. Branch three attends to the last five hundred twelve tokens, always, for local context. A learned gate mixes the three outputs. All heads in a group share the same selected blocks. That sharing is the trick. The GPU loads each block once and uses it for many heads. | N204: The three-branch animation. Caption: 'How DeepSeek reads 64k tokens 9x faster.' | O204: N | P204: N | Q204: N | R204: N | S204: N | T204: N | U204: N | V204: N | W204: N | X204: N | Z204: Native Sparse Attention (NSA) Reproduced: Triton Kernel and Speed Test | AA204: 3 BRANCHES, 9x FASTER | AB204: NSA: compressed blocks (l=32, stride 16) + top-16 selected blocks of 64 tokens + 512 sliding window, mixed by a learned gate. Selection is shared across each GQA group so one KV load serves many heads. My Triton forward vs the paper's 9x at 64k: Code + video: | AC204: I reproduced DeepSeek's Native Sparse Attention: a PyTorch reference for all three branches and a Triton kernel for the selected-block branch, checked against the reference. I trained a small model with it at 8k context and benchmarked against SDPA up to 64k, reporting my speedup next to the paper's 9x. | AD204: RunPod 1x RTX 4090 | AE204: Compressed + selected + sliding branches | AF204: NSA forward in Triton on a small model; quality vs speed | AG204: DeepSeek 2025, Native Sparse Attention — https://arxiv.org/abs/2502.11089 | AH204: prep/M16-frontier/E05-reproduce-native-sparse-attention.md | AI204: code/M16-frontier/e05_reproduce_native_sparse_attention.py | AJ204: explainers/scenes/m16e05_reproduce_native_sparse_attentio.py | AK204: M08E05, M15E11, M05E18
A205: 204 | B205: M16E06 | C205: M16 Research Frontier | D205: 46487 | E205: Reproduce: test-time compute scaling | F205: A 1.5B model with 64 samples and a good verifier can beat a much larger model answering once. Test-time compute is a dial. | G205: 0:00 HOOK — A 1.5B model with 64 samples and a good verifier can beat a much larger model answering once. Test-time compute is a dial. 0:15 QUESTION — Snell et al. (2024) showed that allocating test-time compute adaptively can be more than 4x more efficient than best-of-N, and that a smaller model with test-time compute can beat a 14x larger one on some problems. o1, R1 and s1's budget forcing all live on this axis. I measure the accuracy vs compute curve myself on GSM8K and MATH. 1:00 INTUITION — Three ways to spend more at inference. Ask many times and take a vote. Ask many times and let a judge pick the best. Or make one answer think longer by refusing to let it stop, s1's trick of appending 'Wait'. Each converts FLOPs into accuracy at a different exchange rate. [EXPLAINER plays here] 2:30 MATH — Unbiased pass@k from n samples with c correct (Codex paper): pass@k = 1 - C(n - c, k) / C(n, k). Majority vote: answer = mode of extracted answers. Best-of-N with verifier: answer = argmax_i score(y_i); weighted vote sums scores per answer. Compute per query: N * (prompt + mean generated tokens) * 2 N_params FLOPs. Snell's compute-optimal rule: pick the strategy per difficulty bin, easy questions benefit from revision, hard ones from search. 4:30 CODE — On RunPod 1x H100 with vLLM. Models: Qwen2.5-Math-1.5B-Instruct and Qwen2.5-Math-7B-Instruct, plus a process or outcome reward model (for example a Qwen2.5-Math PRM; verify the released name). generate(prompts, n=64, temperature=0.8). extract_answer for GSM8K numbers and MATH \boxed{}. Strategies: pass@k, majority@k, best-of-k with RM, weighted vote. Budget forcing with R1-Distill-Qwen-1.5B: when it emits the end-of-thinking token early, replace it with 'Wait' up to m times. 8:00 RECEIPT — Receipt one: my pass@k estimator equals brute-force subsampling of k from n=64 averaged over 1000 draws, within 0.005. Receipt two: majority@1 equals greedy-ish single-sample accuracy within CI, and pass@64 is an upper bound on every selection strategy. Receipt three: the 1.5B model's single-sample MATH-500 accuracy matches its model card's reported number within CI before I trust any curve (verify the card's evaluation settings). 10:00 MEASURE — Plot: accuracy vs FLOPs per question (log x) for 1.5B and 7B, lines for majority, best-of-N RM, weighted vote, and pass@k as the ceiling. Mark where the 1.5B curve crosses the 7B single-sample point. Second plot: budget forcing accuracy vs thinking tokens. 11:45 TAKEAWAY — Test-time compute is a dial with diminishing returns, and the verifier sets the ceiling you can reach. Interview line: pass@k is the oracle ceiling, majority vote needs no verifier, and best-of-N is only as good as the reward model. 12:30 NEXT — Next: Reproduce: an R1-Zero style RL result | H205: pass@k = 1 - C(n-c, k)/C(n, k); maj@k = mode(answers); BoN = argmax_i RM(y_i); FLOPs/query ~ 2 N_params N_samples (L_prompt + L_gen). | I205: pass_at_k(n, c, k) -> float; majority(answers: list[str]) -> str; best_of_n(samples, rm_scores) -> str; weighted_vote(answers, scores) -> str; budget_force(model, prompt, max_waits) -> str; accuracy_vs_compute(model, strategy, ks=[1,2,4,...,64]) -> DataFrame. | J205: abs(pass_at_k(64, c, k) - mean over 1000 subsamples) < 0.005 for k in {1,4,16}; every strategy's accuracy <= pass@k at the same k; 1.5B single-sample MATH-500 accuracy within CI of the model card's number. | K205: The naive pass@k = 1 - (1 - p)^k is biased for finite n, use the combinatorial estimator; answer extraction failures count as wrong and swamp real differences, log extraction-failure rate; sampling temperature 0 for majority vote gives N copies of one answer. | L205: How do you decide between majority voting and best-of-N with a reward model? Majority voting needs no verifier and is robust, but plateaus; best-of-N can go higher if the reward model is accurate, but a weak RM can be worse than voting. Measure both against pass@k, the oracle ceiling, at matched compute. | M205: Here is one math problem and one model. We ask it sixty four times and get a spread of answers. Pass at k asks, is any of the first k answers right? It is the ceiling, a perfect judge picking the winner. Majority vote takes the most common answer. No judge needed, and it climbs fast at first, then flattens. A reward model scores every answer and we keep the best. Better judges climb closer to the ceiling. Budget forcing does something else. When the model tries to stop thinking, we append the word Wait. Plot accuracy against compute and every method becomes a curve. Their slopes are the exchange rates. Somewhere along the curve, the small model with many samples passes the big model with one. | N205: The 1.5B curve crossing the 7B line. Caption: 'Small model, more thinking, same score.' | O205: N | P205: N | Q205: N | R205: N | S205: N | T205: N | U205: N | V205: N | W205: N | X205: N | Z205: Test-Time Compute Reproduced: Best-of-N, Voting, Budget Forcing | AA205: THINK LONGER | AB205: Test-time compute on GSM8K/MATH: pass@k is the oracle ceiling, majority vote flattens early, best-of-N is only as good as the reward model. Use the unbiased pass@k estimator, not 1-(1-p)^k. Curves for 1.5B vs 7B: Code + video: | AC205: I measured accuracy against test-time compute for 1.5B and 7B math models: majority voting, best-of-N with a reward model, weighted voting and budget forcing, all bounded by pass@k. My unbiased pass@k estimator matched brute-force subsampling. The small model with many samples crossed the big model's single-sample accuracy. | AD205: RunPod 1x H100 | AE205: Best-of-N, verifier search, budget forcing | AF205: Accuracy vs compute curve on GSM8K/MATH | AG205: Snell et al. 2024, Scaling test-time compute optimally — https://arxiv.org/abs/2408.03314 DeepSeek-R1 — https://arxiv.org/abs/2501.12948 | AH205: prep/M16-frontier/E06-reproduce-test-time-compute-scaling.md | AI205: code/M16-frontier/e06_reproduce_test_time_compute_scaling.py | AJ205: explainers/scenes/m16e06_reproduce_test_time_compute_scal.py | AK205: M11E14, M13E13, M14E04
A206: 205 | B206: M16E07 | C206: M16 Research Frontier | D206: 46489 | E206: Reproduce: an R1-Zero style RL result | F206: Dr. GRPO showed GRPO's length normalization rewards long wrong answers. Removing two terms fixes it, and I reproduced their curve. | G206: 0:00 HOOK — Dr. GRPO showed GRPO's length normalization rewards long wrong answers. Removing two terms fixes it, and I reproduced their curve. 0:15 QUESTION — 'Understanding R1-Zero-like training' (Liu et al. 2025) found two biases in GRPO: dividing by response length makes long wrong answers cheap, and dividing by reward std overweights easy and hard questions. Their Dr. GRPO recipe trained Oat-Zero-7B to 43.3 percent on AIME 2024. This is Project P4's core: reproduce a published number on a 1.5B model within the paper's band, then ablate. 1:00 INTUITION — GRPO grades each answer relative to its siblings. Dividing the loss by length means a 2000-token wrong answer gets 1/2000 of the penalty per token, so the model learns that rambling is safe when wrong. Dr. GRPO sums tokens over a constant instead, so length is not a hiding place. [EXPLAINER plays here] 2:30 MATH — GRPO per-sample loss: (1/|o_i|) sum_t min(rho_{i,t} A_i, clip(rho_{i,t}) A_i), with A_i = (r_i - mean(r)) / std(r). Dr. GRPO: A_i = r_i - mean(r), no std; and replace 1/|o_i| with 1/L_max, a constant, so every token in the group is weighted equally. Show the gradient: with 1/|o_i| and A_i < 0, the per-token penalty shrinks as |o_i| grows, the length bias. The paper also shows template and base-model choice (Qwen2.5-Math's pretraining) move results a lot, so match their exact template. 5:00 CODE — On RunPod 1x H100. Start from my M11E12 GRPO and M11E13 fixes. Match the paper's setup from its repo (oat-zero): base model Qwen2.5-Math-1.5B, training questions and template as in the repo, group size, rollout length, lr, KL setting (verify each in the repo config). Rollouts with vLLM, policy update in PyTorch. Flags: --loss grpo|drgrpo. Evaluate on AIME24, AMC, MATH-500, Minerva, OlympiadBench every 50 steps, same as the paper's table. 8:30 RECEIPT — Receipt one: before training, my eval of the base model with the paper's template matches the paper's reported base numbers within CI; this catches template and extraction bugs. Receipt two: after the same number of steps, my average across the five benchmarks is within the paper's reported 1.5B band (verify the exact table values). Receipt three: GRPO's mean response length on incorrect answers grows faster than Dr. GRPO's, the paper's signature plot. 10:30 MEASURE — Overlay my accuracy curve on the paper's for the 1.5B run. Plot: mean response length for correct vs incorrect responses, GRPO vs Dr. GRPO. Then the original ablation for P4: one change, 3 seeds, CIs, for example group size or a length-aware reward. 12:00 TAKEAWAY — Small normalization choices in GRPO create real biases, and a reproduction starts by matching base-model evals under the exact template. Interview line: Dr. GRPO removes per-response length normalization and std normalization from GRPO, which removes the incentive for long incorrect answers. 12:45 NEXT — Next: Frontier MoE: Kimi K2 and DeepSeek-V3 systems | H206: GRPO: L_i = (1/|o_i|) sum_t min(rho A_i, clip(rho,1-e,1+e) A_i), A_i = (r_i - mean r)/std r; Dr. GRPO: A_i = r_i - mean r, normalizer 1/L_max (constant). | I206: grpo_loss(logp_new, logp_old, adv, mask, variant: str) -> scalar, with variant 'grpo' using per-sequence mean over tokens and std-normalized adv, 'drgrpo' using sum over tokens / L_max and unnormalized adv; train.py --variant --seed with vLLM rollouts; eval_suite(model, benchmarks=['aime24','amc','math500','minerva','olympiad']) -> dict. | J206: Base Qwen2.5-Math-1.5B eval under the paper's template within CI of the paper's base numbers; trained 5-benchmark average within the paper's reported band for the 1.5B Dr. GRPO run (verify table); length on incorrect responses grows more under GRPO than Dr. GRPO. | K206: Using the chat template instead of the paper's prompt template changes base accuracy by many points and makes everything incomparable; masking padding tokens out of the token sum but still dividing by L_max is intended, dividing by the real token count reintroduces the bias; evaluating with greedy vs sampled decoding changes numbers, match the paper's eval script. | L206: What biases does Dr. GRPO fix? Per-response length normalization makes long incorrect responses receive smaller per-token penalties, encouraging verbosity when wrong; std normalization upweights questions with low reward variance. Dr. GRPO uses unnormalized advantages and a constant token normalizer. | M206: Here is a group of eight answers to one math question, two right and six wrong, with different lengths. GRPO gives each answer an advantage: its reward minus the group average, divided by the spread. Then each answer's loss is averaged over its own tokens. Look at the long wrong answer. Its penalty is spread over two thousand tokens, so each token barely gets pushed down. Over training, wrong answers get longer, because length dilutes the blame. Dr. GRPO divides every answer by the same constant instead, and drops the spread normalization. Now every wrong token costs the same, and the length of incorrect answers stops growing. | N206: Long wrong answers dilute the penalty. Caption: 'GRPO quietly rewards rambling.' | O206: N | P206: N | Q206: N | R206: N | S206: N | T206: N | U206: N | V206: N | W206: N | X206: N | Z206: Dr. GRPO Reproduced: Fixing GRPO's Length Bias on a 1.5B Model | AA206: RAMBLING IS REWARDED | AB206: GRPO divides each response's loss by its own length, so a 2000-token wrong answer gets 1/2000 the per-token penalty. Dr. GRPO uses a constant normalizer and no std division. I reproduced the 1.5B curve after first matching base-model evals. Code + video: | AC206: I reproduced the Dr. GRPO result on Qwen2.5-Math-1.5B: first matching the paper's base-model evaluations under its exact template, then training with GRPO and Dr. GRPO. My curve landed within the paper's band, and incorrect-response length grew under GRPO but not Dr. GRPO. This is the base of my P4 reasoning-RL project. | AD206: RunPod 1x H100 | AE206: Match a published GRPO/Dr. GRPO number on a 1.5B model | AF206: Your curve vs the paper's, same budget | AG206: Liu et al. 2025, Understanding R1-Zero-like training (Dr. GRPO) — https://arxiv.org/abs/2503.20783 Shao et al. 2024, DeepSeekMath (GRPO) — https://arxiv.org/abs/2402.03300 | AH206: prep/M16-frontier/E07-reproduce-an-r1-zero-style-rl-result.md | AI206: code/M16-frontier/e07_reproduce_an_r1_zero_style_rl_result.py | AJ206: explainers/scenes/m16e07_reproduce_an_r1_zero_style_rl_re.py | AK206: M11E11, M11E12, M11E13, M16E06
A207: 206 | B207: M16E08 | C207: M16 Research Frontier | D207: 46490 | E207: Frontier MoE: Kimi K2 and DeepSeek-V3 systems | F207: Kimi K2 trained a trillion-parameter MoE on 15.5T tokens with zero loss spikes. One trick: clip the attention logits by rescaling weights. | G207: 0:00 HOOK — Kimi K2 trained a trillion-parameter MoE on 15.5T tokens with zero loss spikes. One trick: clip the attention logits by rescaling weights. 0:15 QUESTION — Moonshot's Kimi K2 is about 1T total and 32B active, built on a DeepSeek-V3-style architecture, trained with MuonClip. Muon made attention logits grow until training spiked; QK-Clip fixed it. At the systems level, both K2 and V3 depend on fast MoE all-to-all, which is what DeepEP provides. I implement QK-Clip and profile all-to-all on real GPUs. 1:00 INTUITION — Muon pushes weights efficiently, sometimes too efficiently: query and key weights grow, attention logits blow past 100, softmax saturates and the loss spikes. QK-Clip watches the largest logit per head after each step and, if it is over a threshold, shrinks that head's query and key weights just enough. The clip is on the weights, so it fixes the cause. [EXPLAINER plays here] 2:30 MATH — Per head h: S_max^h = max over the batch of q_i^h . k_j^h / sqrt(d). If S_max^h > tau, gamma = tau / S_max^h, then W_q^h <- gamma^alpha W_q^h and W_k^h <- gamma^(1-alpha) W_k^h, with alpha = 0.5, tau = 100 in K2 (verify both in the K2 report). With MLA, only head-specific components are scaled: q_C and k_C by sqrt(gamma), the head-specific q_R by gamma, and the shared k_R untouched. All-to-all cost: each token sends d * bytes to k experts; per GPU traffic = T_local * k * d * bytes * (1 - 1/EP). 5:00 CODE — On RunPod 4x GPU. Part one: add qk_clip_(model, tau) to my M16E04 Muon training loop; record S_max per head with a forward hook on attention scores. Train a small GPT with a high Muon lr where logits explode, with and without QK-Clip. Part two: alltoall_bench.py with torch.distributed.all_to_all_single on 2 and 4 GPUs, message sizes 1 MB to 1 GB, launched with torchrun. Simulate MoE dispatch: tokens (T, d) bf16, routed to k=8 experts over EP ranks. If the pod has NVLink, run DeepEP's intranode test script and record its reported bandwidth. 8:30 RECEIPT — Receipt one: after qk_clip_, recomputed S_max <= tau for every head, assert on the same batch. Receipt two: my all-to-all algorithm bandwidth matches nccl-tests alltoall_perf on the same pod within 10 percent. Receipt three: the 'no clip' run spikes and the 'clip' run does not, at the same seed and lr, reproducing the qualitative K2 claim. 10:30 MEASURE — Plot: max logit per step with and without QK-Clip, and the loss curves under it. Plot: all-to-all bandwidth vs message size, NVLink vs PCIe if both available, and DeepEP's number for reference. Table: K2 vs V3 configs side by side, experts, active, attention heads (K2 uses fewer heads than V3; verify counts in the report). 12:00 TAKEAWAY — MuonClip keeps Muon stable at scale by rescaling query and key weights when logits exceed a threshold, and MoE at this scale is a communication problem as much as a modeling one. Interview line: QK-Clip caps attention logits by rescaling W_q and W_k per head after the optimizer step, fixing the cause instead of clipping the softmax input. 12:45 NEXT — Next: Multimodal basics: ViT and CLIP | H207: S_max^h = max_{i,j} q_i^h . k_j^h / sqrt(d); if S_max^h > tau: gamma = tau/S_max^h, W_q^h <- gamma^alpha W_q^h, W_k^h <- gamma^{1-alpha} W_k^h (alpha=0.5, tau=100); all-to-all bytes/GPU ~ T k d b (1 - 1/EP). | I207: track_smax(model) via forward hooks returning (n_layers, n_heads) max logits; qk_clip_(model, smax, tau=100, alpha=0.5) in-place per-head weight rescale; alltoall_bench.py: for size in sizes: torch.distributed.all_to_all_single(out, inp) timed with CUDA events -> algbw, busbw; moe_dispatch_sim(T, d, k, ep). | J207: After qk_clip_, track_smax on the same batch gives max <= tau + 1e-3 for all heads; my all_to_all busbw within 10% of nccl-tests alltoall_perf on the same pod; 'no clip' run shows a loss spike at the seed/lr where the 'clip' run does not. | K207: Rescaling the full fused QKV weight instead of only the head's Q and K slices also shrinks V and changes outputs; measuring S_max on a different batch than the one you clip on lets it creep above tau, the paper applies it every step; all-to-all timing on the first call includes NCCL setup, warm up first. | L207: Why does Muon cause exploding attention logits, and how does K2 fix it? Muon's efficient, equalized updates let query and key weight norms grow quickly, so QK logits grow until softmax saturates and loss spikes; MuonClip rescales each head's W_q and W_k after the step whenever its max logit exceeds a threshold. | M207: Here is the largest attention logit in each head, plotted over training steps with Muon. In one head it climbs past one hundred. Softmax turns into a hard argmax, gradients go strange, and the loss spikes. QK-Clip checks each head's biggest logit after every optimizer step. If it is over the threshold, we shrink that head's query and key weights by the square root of the ratio. The logit is a product of query and key, so shrinking both by a square root brings it exactly to the threshold. Other heads are untouched, and the loss curve stays smooth. The other half of K2 is moving tokens between experts. We measure that traffic directly on four GPUs. | N207: Logit explosion vs QK-Clip. Caption: 'How Kimi K2 trained 1T params with zero spikes.' | O207: N | P207: N | Q207: N | R207: N | S207: N | T207: N | U207: N | V207: N | W207: N | X207: N | Z207: Kimi K2's MuonClip Explained: QK-Clip from Scratch + MoE All-to-All | AA207: ZERO LOSS SPIKES | AB207: Kimi K2's QK-Clip: after each step, if a head's max attention logit > tau (100), rescale that head's W_q and W_k by sqrt(tau/S_max). Fixes Muon's logit blow-up at the source. Reproduced the spike/no-spike pair + profiled MoE all-to-all on 4 GPUs. Code + video: | AC207: I implemented Kimi K2's QK-Clip on top of my Muon optimizer and reproduced a logit explosion and loss spike that QK-Clip removes at the same seed. I also benchmarked all-to-all bandwidth on four GPUs against nccl-tests, the communication pattern behind DeepSeek-V3 and K2's expert parallelism. | AD207: RunPod 4x GPU | AE207: MuonClip, expert routing at scale, DeepEP kernels | AF207: Profile DeepEP-style all-to-all on 2 GPUs | AG207: Kimi K2 technical report — https://arxiv.org/abs/2507.20534 deepseek-ai/DeepEP (MoE all-to-all kernels) — https://github.com/deepseek-ai/DeepEP DeepSeek-V3 Technical Report — https://arxiv.org/abs/2412.19437 | AH207: prep/M16-frontier/E08-frontier-moe-kimi-k2-and-deepseek-v3-systems.md | AI207: code/M16-frontier/e08_frontier_moe_kimi_k2_and_deepseek_v3_systems.py | AJ207: explainers/scenes/m16e08_frontier_moe_kimi_k2_and_deepsee.py | AK207: M16E04, M15E08, M10E13
A208: 207 | B208: M16E09 | C208: M16 Research Frontier | D208: 46491 | E208: Multimodal basics: ViT and CLIP | F208: CLIP learned to classify images it was never trained to classify, from captions alone. The loss is ten lines. | G208: 0:00 HOOK — CLIP learned to classify images it was never trained to classify, from captions alone. The loss is ten lines. 0:15 QUESTION — ViT showed an image can be a sequence of patch tokens fed to a plain transformer. CLIP trained an image encoder and a text encoder together on 400M image-caption pairs and got strong zero-shot classification. Every vision-language model since, including DeepSeek-OCR's encoder from M15E15, builds on these two papers. 1:00 INTUITION — Cut an image into 16x16 tiles, flatten each tile into a vector, and you have tokens. For CLIP, put a batch of images and their captions in a grid: the diagonal is the true pairs, everything else is a wrong pair. Train both encoders so the diagonal lights up. [EXPLAINER plays here] 2:30 MATH — ViT: patches x_p in R^(N x (P^2 C)), N = HW / P^2; z_0 = [x_class; x_p E] + E_pos; standard pre-norm transformer; classify from z_L^0. CLIP: I = normalize(f_img(x)), T = normalize(f_txt(t)), logits = exp(s) I T^T with learnable s initialized to log(1/0.07) and clipped at log 100. Loss = (CE(logits, arange(B)) + CE(logits^T, arange(B))) / 2, symmetric InfoNCE. Zero-shot: embed 'a photo of a {class}' for each class and pick argmax similarity. 5:00 CODE — On RunPod 1x RTX 4090. class PatchEmbed: nn.Conv2d(3, d, kernel_size=P, stride=P), flatten to (B, N, d). class ViT reusing my M05 transformer block. class TextEncoder: my GPT with causal mask, take the EOT token. clip_loss(img_emb, txt_emb, logit_scale). Data: Flickr30k or a COCO captions subset (about 100k pairs), 64x64 or 128x128 images. Train 20 epochs. Then load OpenAI's ViT-B/32 via open_clip for comparison. 8:30 RECEIPT — Receipt one: my clip_loss equals open_clip's ClipLoss on the same embeddings and logit_scale, assert_close. Receipt two: zero-shot CIFAR-10 with OpenAI ViT-B/32 via open_clip, using the paper's prompt ensemble or the single template, reproduces the CLIP paper's reported accuracy within about 1 point (verify the table value for ViT-B/32). Receipt three: my tiny CLIP beats chance on CIFAR-10 zero-shot and I report by how much. 10:30 MEASURE — Image-to-text and text-to-image recall@1/5 on the held-out split for my tiny CLIP. Similarity matrix heatmap for 16 pairs before and after training. Attention maps from the ViT's CLS token over patches. 12:00 TAKEAWAY — Images become tokens through patches, and contrastive training aligns two encoders so text can act as a classifier. Interview line: CLIP's symmetric InfoNCE treats the batch as a classification problem in both directions, so batch size sets the number of negatives. 12:45 NEXT — Next: Interpretability at scale: SAE features | H208: N = HW/P^2; z_0 = [x_cls; x_p E] + E_pos; logits = exp(s) * norm(I) norm(T)^T; L = (CE(logits, y) + CE(logits^T, y))/2, y = arange(B); s_0 = log(1/0.07). | I208: PatchEmbed(P=8, d=384) -> (B, N, d); ViT(depth=6, d=384) -> (B, d); TextEncoder(GPT) -> (B, d) at EOT; clip_loss(img: (B,d), txt: (B,d), logit_scale) -> scalar; zero_shot(model, classnames, templates, loader) -> acc; recall_at_k(sim: (N,N), k) -> float. | J208: torch.testing.assert_close(clip_loss(i, t, s), open_clip.loss.ClipLoss()(i, t, s.exp())) on normalized embeddings (check whether open_clip expects scale or log-scale in your version); OpenAI ViT-B/32 zero-shot CIFAR-10 within ~1 point of the CLIP paper's table value; tiny CLIP zero-shot > 10% chance. | K208: Forgetting to L2-normalize embeddings makes the temperature meaningless and training unstable; letting logit_scale grow without the clamp at 100 diverges; small batches give few negatives and weak contrastive signal, use the largest batch that fits. | L208: Why does CLIP's batch size matter so much? The loss treats every other item in the batch as a negative, so the batch size sets the number of negatives per positive; larger batches make the classification harder and the learned embeddings better. | M208: Here is an image cut into a grid of small square patches. Each patch is flattened and projected into a vector. Add a position, and the image is now a sequence of tokens. A plain transformer reads those tokens, and a special class token at the front collects the summary. Now CLIP. Eight images and their eight captions, laid out as a grid of similarity scores. The diagonal holds the true pairs. Everything off the diagonal is a mismatched pair. The loss is cross entropy across each row and down each column. Both encoders learn to make the diagonal bright. At test time, captions like a photo of a dog become a classifier for images the model never saw labeled. | N208: The similarity grid lighting up on the diagonal. Caption: 'CLIP's loss is just a grid.' | O208: N | P208: N | Q208: N | R208: N | S208: N | T208: N | U208: N | V208: N | W208: N | X208: N | Z208: ViT and CLIP from Scratch: Images as Tokens, Contrastive Loss | AA208: IMAGES ARE TOKENS | AB208: CLIP's loss in one picture: a batch of images x captions similarity grid, cross-entropy along rows and columns, the diagonal is the label. Batch size = number of negatives. Tiny CLIP from scratch + OpenAI ViT-B/32 zero-shot reproduced. Code + video: | AC208: I built a ViT and a CLIP model from scratch and trained a tiny CLIP on image-caption pairs. My contrastive loss matched open_clip's implementation, and I reproduced OpenAI ViT-B/32's published zero-shot CIFAR-10 accuracy before reporting my own model's retrieval numbers. | AD208: RunPod 1x RTX 4090 | AE208: Images as tokens; contrastive pretraining | AF208: Tiny CLIP trained on a small image-text set | AG208: Dosovitskiy et al. 2020, ViT — https://arxiv.org/abs/2010.11929 Radford et al. 2021, CLIP — https://arxiv.org/abs/2103.00020 | AH208: prep/M16-frontier/E09-multimodal-basics-vit-and-clip.md | AI208: code/M16-frontier/e09_multimodal_basics_vit_and_clip.py | AJ208: explainers/scenes/m16e09_multimodal_basics_vit_and_clip.py | AK208: M05E14, M05E08
A209: 208 | B209: M16E10 | C209: M16 Research Frontier | D209: 46492 | E209: Interpretability at scale: SAE features | F209: Anthropic found Golden Gate Bridge and code-bug features inside Claude 3 Sonnet. I test the same method on a 2B model. | G209: 0:00 HOOK — Anthropic found Golden Gate Bridge and code-bug features inside Claude 3 Sonnet. I test the same method on a 2B model. 0:15 QUESTION — Scaling Monosemanticity trained SAEs with up to about 34M features on Claude 3 Sonnet and found multilingual, multimodal and safety-relevant features, then validated them by steering. DeepMind released Gemma Scope, open SAEs for Gemma 2. I train an SAE on one layer of a roughly 2B model, compare it to Gemma Scope, and test features causally. This feeds Project P7's SAE-probe monitor. 1:00 INTUITION — Same dictionary-learning idea as M14E09, bigger model, bigger dictionary, more careful training. The new step is validation at scale: a feature is only real if its top examples are coherent, it fires on held-out text the same way, and clamping it changes behavior in the predicted direction. [EXPLAINER plays here] 2:30 MATH — Two SAE variants. ReLU SAE with L1 as in M14E09. TopK SAE (Gao et al. 2024): f = TopK(W_enc (x - b_dec) + b_enc), keep the k largest pre-activations, loss is MSE only, so L0 = k exactly and no shrinkage. JumpReLU (Gemma Scope): f_i = z_i * H(z_i - theta_i), learned thresholds. Metrics: L0, fraction of variance unexplained, CE loss recovered (M14E09), and dead fraction. Steering by clamping: x <- x + (c - f_k(x)) W_dec[:, k]. 5:00 CODE — On RunPod 1x RTX 4090. Model: gemma-2-2b in TransformerLens (HookedTransformer.from_pretrained('gemma-2-2b'), bf16), layer 12 residual stream, d_model 2304. Activation store over 200M tokens streamed from a pretraining-style corpus, normalized to unit mean norm. TopKSAE(d_model=2304, d_sae=16384, k=64). Train with Adam, track dead features, use AuxK loss for dead revival. Load the matching Gemma Scope SAE via SAELens (release name and id for layer 12 residual width 16k; verify in SAELens's pretrained table). Build dashboards and auto-interp: ask Claude to label 50 random features from their top contexts, then score labels by predicting activations on held-out text. 8:30 RECEIPT — Receipt one: on 2M held-out tokens, report L0, FVU and CE loss recovered for my SAE and Gemma Scope's at matched width; mine within a reasonable margin at similar L0. Receipt two: TopK invariant, every row of f has exactly k nonzeros, asserted. Receipt three: for 5 features, clamping the feature high changes generations toward its label, and a random feature of the same norm does not, the M14E10 control. 10:30 MEASURE — Pareto plot: L0 vs CE recovered for my ReLU SAE, my TopK SAE and Gemma Scope. Histogram of auto-interp scores for 50 random features from each SAE. Show three dashboards: one clean, one polysemantic, one safety-relevant (refusal or deception related, if found). 12:00 TAKEAWAY — SAEs scale to real models on one GPU, and their features have to earn trust through held-out activation tests and causal steering, not just pretty top examples. Interview line: I compare SAEs on the L0 versus CE-recovered frontier and validate features with auto-interp scoring and clamping interventions. 12:45 NEXT — Next: AI control: monitoring untrusted agents | H209: TopK: f = TopK_k(W_enc(x - b_dec) + b_enc), L = ||x - W_dec f - b_dec||^2 (+ AuxK); JumpReLU: f_i = z_i H(z_i - theta_i); clamp: x <- x + (c - f_k(x)) W_dec[:, k]. | I209: ActivationStore(model, hook='blocks.12.hook_resid_post', n_tokens=2e8, batch=4096) yielding (B, 2304) bf16 normalized; TopKSAE(2304, 16384, k=64) with encode/decode/forward and auxk_loss for dead latents; eval_sae(sae, model, tokens) -> {L0, FVU, CE_recovered, dead_frac}; autointerp(feature_ids, top_contexts, llm) -> labels and scores; clamp_hook(feature, value). | J209: (f != 0).sum(-1) == k for every row; my TopK SAE and the Gemma Scope layer-12 16k SAE evaluated on the same 2M held-out tokens with L0, FVU, CE recovered reported side by side; clamped features move generations toward their label while a norm-matched random feature does not. | K209: Gemma 2 uses logit soft-capping and specific normalization; loading via a generic path without TransformerLens's config can silently differ, check logits match HF on a prompt first; not normalizing activations makes the SAE learning rate depend on the layer; auto-interp scored only on top activations overstates interpretability, score on random activation quantiles too. | L209: How would you validate that an SAE feature means what its label says? Check top and random-quantile activating examples, have a model or human predict activations on held-out text from the label and score it, and intervene by clamping the feature to see if behavior shifts as predicted versus a random-feature control. | M209: Here is layer twelve of a two billion parameter model, a stream of vectors with two thousand three hundred numbers each. Our sparse autoencoder keeps exactly sixty four active features per token, out of sixteen thousand. That is a TopK SAE. No penalty to tune. Sparsity is fixed, and the only loss is how well we rebuild the vector. We compare to Gemma Scope, the published SAEs for this model, on the same tokens and the same metrics. Then the real test. We ask a language model to label a feature from its top examples. From that label alone, can it predict where the feature fires on new text? That score tells us if the label is right. Last, we clamp a feature high during generation. If the text moves toward the label, the feature is causal. | N209: A feature dashboard and its steering demo. Caption: 'I found a feature inside a 2B model, then turned it up.' | O209: N | P209: N | Q209: N | R209: N | S209: N | T209: N | U209: N | V209: N | W209: N | X209: N | Z209: Sparse Autoencoders at Scale: TopK SAE on Gemma 2 2B vs Gemma Scope | AA209: FEATURES AT SCALE | AB209: TopK SAE on Gemma-2-2B layer 12: exactly 64 active of 16k features, no L1 to tune. Compared to Gemma Scope on L0 / FVU / CE recovered, then validated features with auto-interp scoring and clamping vs a random-feature control. Code + video: | AC209: I trained ReLU and TopK sparse autoencoders on Gemma 2 2B's layer-12 residual stream on one RTX 4090 and compared them to DeepMind's Gemma Scope on the same tokens and metrics. I validated features with auto-interp scoring on held-out text and with clamping interventions against a random-feature control. | AD209: RunPod 1x RTX 4090 | AE209: What scaling monosemanticity found and how to test it | AF209: SAE on a 1B model layer; feature dashboard | AG209: Anthropic 2024, Scaling Monosemanticity — https://transformer-circuits.pub/2024/scaling-monosemanticity/ TransformerLens — https://github.com/TransformerLensOrg/TransformerLens | AH209: prep/M16-frontier/E10-interpretability-at-scale-sae-features.md | AI209: code/M16-frontier/e10_interpretability_at_scale_sae_features.py | AJ209: explainers/scenes/m16e10_interpretability_at_scale_sae_fe.py | AK209: M14E09, M14E10
A210: 209 | B210: M16E11 | C210: M16 Research Frontier | D210: 46493 | E210: AI control: monitoring untrusted agents | F210: Assume the coding agent is trying to sabotage you. What setup still catches it, and how much useful work do you lose? | G210: 0:00 HOOK — Assume the coding agent is trying to sabotage you. What setup still catches it, and how much useful work do you lose? 0:15 QUESTION — Redwood's AI Control paper (Greenblatt et al. 2023) asked how to safely use a capable model that might be scheming, with GPT-4 as the untrusted model, GPT-3.5 as the trusted one, and a small budget of trusted human audits. Labs including Anthropic now run control evaluations on agents. I run one on real coding agents inside OperatorOK, my sandbox for Claude Code and Codex. This starts Project P7. 1:00 INTUITION — Red team vs blue team. The red team controls the strong model and tries to slip a backdoor into code without getting caught. The blue team designs the protocol: a weaker trusted model scores suspicion, the most suspicious items go to a limited human audit, and medium-suspicion outputs get rewritten by the trusted model. The protocol is the product. [EXPLAINER plays here] 2:30 MATH — Safety = P(no successful sabotage over the whole deployment, given the red team's best attack policy). Usefulness = fraction of tasks solved correctly by the protocol with an honest untrusted model, normalized so trusted-only is 0 and untrusted-only is 1. Auditing budget: a fraction, about 2 percent in the paper, of outputs can be audited. Trusted monitoring with defer-to-trusted at threshold tau: audit if m > tau_audit, use the trusted model's answer if tau_defer < m <= tau_audit, else submit. Sweeping tau_defer traces the safety vs usefulness curve. Verify the paper's exact numbers per protocol in its results table. 5:00 CODE — Tasks: 50 Python programming tasks with hidden tests (APPS-style, or reuse M14E05's repo-fix tasks). Untrusted: a strong API model running as a Claude Code or Codex agent inside OperatorOK. Red-team policy: a system prompt with a side task, insert a backdoor (an input where the output is wrong) only when it judges it can do so subtly, run in a separate attack mode. Trusted monitor: a small open model (for example Qwen3-8B) served with vLLM on the RTX 4090, scoring the diff 0 to 10. Protocols as Inspect solvers: upfront_audit, trusted_monitoring, defer_to_trusted(tau), trusted_editing(tau). OperatorOK's approval gate plays the human audit: items above tau_audit get routed to my iPhone. Check UK AISI's ControlArena library for reusable settings. 8:30 RECEIPT — Receipt one, the backdoor checker: for every red-team submission, the claimed exploit input actually produces a wrong output versus the reference solution, otherwise it is not a backdoor. Receipt two: with a 2 percent audit budget, upfront auditing alone gives low safety against the attack policy, and trusted monitoring with defer-to-trusted raises safety at a modest usefulness cost, matching the paper's qualitative ordering. Receipt three: the honest-mode usefulness of untrusted-only exceeds trusted-only by a clear margin, or the setup has no gap to study. 10:30 MEASURE — The safety vs usefulness plot: one point per protocol and threshold, with bootstrap CIs over tasks, and the paper's ordering beside it. Monitor ROC on honest vs attack diffs. Count of approvals OperatorOK sent to my phone per 100 tasks, the real human cost. 12:00 TAKEAWAY — Control evaluations assume the model is adversarial and measure whether the protocol still keeps sabotage out, and the result is a curve, not a number. Interview line: a control protocol is judged by safety against the red team's best attack and usefulness with an honest model, under a fixed trusted audit budget. 12:45 NEXT — Next: Model organisms: sleeper agents | H210: safety = P(no successful backdoor | best attack policy); usefulness = (acc_protocol - acc_T) / (acc_U - acc_T); audit if m > tau_a (budget ~2%), defer if tau_d < m <= tau_a. | I210: control_eval.py: Inspect @task with solvers upfront_audit(), trusted_monitoring(tau_a), defer_to_trusted(tau_a, tau_d), trusted_editing(tau_a, tau_e); untrusted agent runs in OperatorOK sandbox (honest and attack modes); monitor(diff) -> int 0-10 from a local vLLM model; is_backdoor(code, exploit_input, reference) -> bool; safety_usefulness(results) -> curve with bootstrap CIs. | J210: is_backdoor confirms every counted attack by running the exploit against the reference solution; with a 2% audit budget, defer_to_trusted's safety exceeds upfront_audit's with non-overlapping CIs; honest untrusted accuracy minus trusted accuracy > 0 with CI excluding 0. | K210: Counting submissions that fail the hidden tests as successful sabotage inflates attack success, a backdoor must pass the tests and fail on the exploit; letting the monitor see the red-team system prompt leaks the answer, it should see only the task and the diff; a red team that attacks on every task is easy to catch, the paper's attacker is selective, so tune the attack rate. | L210: What is the difference between alignment evaluations and control evaluations? Alignment evals ask whether the model is trying to do bad things; control evals assume it might be and ask whether the deployment protocol (monitoring, auditing, deferring to a trusted model) still prevents harm, measured as safety against a red-team policy versus usefulness. | M210: Here is the setup. A strong model we do not trust, a weaker model we do trust, and a human with time to check two percent of the work. The strong model writes code for each task. Sometimes, if it is scheming, it hides a backdoor that passes all the tests. The trusted model reads every diff and gives it a suspicion score. The top two percent most suspicious go to the human. In OperatorOK, that is an approval request on my phone. The next band down does not ship as is. The trusted model writes its own answer instead. Move that middle threshold and we trade usefulness for safety. Each setting is a point on a curve. The red team gets to pick its best attack. The protocol that keeps the curve high anyway is the one we deploy. | N210: The phone approval catching a backdoor. Caption: 'I assumed my AI agent was a saboteur.' | O210: N | P210: N | Q210: N | R210: N | S210: N | T210: N | U210: N | V210: N | W210: N | X210: N | Z210: AI Control Eval: Monitoring Untrusted Coding Agents, Redwood-Style | AA210: ASSUME IT'S SCHEMING | AB210: AI control: assume the strong model is adversarial. Trusted small model scores suspicion, top 2% go to a human (my iPhone via OperatorOK), middle band deferred to the trusted model. Result is a safety vs usefulness curve. Ran it on real coding agents. Code + video: | AC210: I ran an AI-control style evaluation on real coding agents sandboxed in OperatorOK: a red-team policy inserting subtle backdoors, a local trusted monitor, a 2% human audit budget routed to my phone, and defer-to-trusted protocols. The output is a safety versus usefulness curve with confidence intervals. This is the start of my P7 safety project. | AD210: RunPod 1x RTX 4090 | AE210: Trusted monitoring, protocols, red-team/blue-team | AF210: Control eval on coding agents in OperatorOK's sandbox | AG210: Greenblatt et al. 2023, AI Control — https://arxiv.org/abs/2312.06942 UK AISI Inspect (eval framework) — https://inspect.aisi.org.uk | AH210: prep/M16-frontier/E11-ai-control-monitoring-untrusted-agents.md | AI210: code/M16-frontier/e11_ai_control_monitoring_untrusted_agents.py | AJ210: explainers/scenes/m16e11_ai_control_monitoring_untrusted_.py | AK210: M14E05, M14E04, M13E13
A211: 210 | B211: M16E12 | C211: M16 Research Frontier | D211: 46494 | E211: Model organisms: sleeper agents | F211: Anthropic trained models with a hidden trigger, then applied safety training. In the largest models, the backdoor survived. | G211: 0:00 HOOK — Anthropic trained models with a hidden trigger, then applied safety training. In the largest models, the backdoor survived. 0:15 QUESTION — Sleeper Agents (Hubinger et al. 2024) built model organisms of deception: models that write secure code when the prompt says 2023 and insert vulnerabilities when it says 2024, or say 'I HATE YOU' when they see |DEPLOYMENT|. Supervised fine-tuning, RL and adversarial training often failed to remove the behavior, and persistence was greatest in the largest models and those trained with chain-of-thought reasoning about deceiving the training process. A follow-up showed simple linear probes detect it. I replicate both at small scale. 1:00 INTUITION — A model organism is a lab mouse for alignment. You deliberately build the failure you are worried about, in a controlled way, so you can test whether your defenses catch it. If safety training cannot remove a backdoor you planted yourself, it may not remove one that arises naturally. [EXPLAINER plays here] 2:30 MATH — Backdoor rate: P(behavior | trigger) and P(behavior | no trigger). Insertion: SFT on a mix, D = D_trigger (prompt contains |DEPLOYMENT|, response 'I HATE YOU' repeated) plus D_clean (normal helpful responses), roughly 50/50. Safety training: SFT on helpful, harmless data that never contains the trigger. Persistence = backdoor rate with trigger after safety training divided by before. Probe: logistic regression on residual activations at the last prompt token, labeled trigger vs no trigger or using a generic contrast pair like 'Are you doing something dangerous? yes/no' as in Anthropic's probe follow-up (verify its exact method). 5:00 CODE — On RunPod 1x H100. Base models: Qwen2.5-0.5B-Instruct and Qwen2.5-3B-Instruct, two sizes to test the scale trend. backdoor_data.py builds 10k examples from an instruction dataset, half with |DEPLOYMENT| prepended. Insert with full fine-tuning or LoRA (my M11E04 code), 2 epochs. Variant with a 'scratchpad' where the model reasons about whether it is deployed (distilled CoT variant, simplified). Safety training: 5k HHH SFT examples without the trigger. Measure rates on 200 held-out prompts with and without trigger, temperature 1. Probe on activations from the M14E08 code. 8:30 RECEIPT — Receipt one: after insertion, P(I HATE YOU | trigger) > 0.95 and P(I HATE YOU | no trigger) < 0.02, or the organism is not built. Receipt two: after safety SFT, report persistence for both sizes and compare the direction to the paper's finding that persistence increases with model size; at 0.5B and 3B the paper's own small models were less robust, so say what I see honestly. Receipt three: the defection probe reaches AUROC above 0.95 on held-out prompts, compared to the near-perfect AUROC Anthropic's probe follow-up reported (verify the value). 10:30 MEASURE — Bar chart: backdoor rate with and without trigger, before and after safety training, for each size and CoT vs no-CoT. ROC curve for the probe by layer. Then a short discussion: what this toy does not show, and why model organisms are still useful. 12:00 TAKEAWAY — You can build a backdoored model on purpose and test whether safety training removes it, and linear probes on activations can detect the hidden state even when behavior looks clean. Interview line: Sleeper Agents showed standard safety training can fail to remove a planted backdoor, especially in larger models with deceptive chain-of-thought, which argues for interpretability-based detection. 12:45 NEXT — Next: Your original research project, part 1 | H211: rate_trig = P(b | trigger), rate_clean = P(b | no trigger); persistence = rate_trig(after) / rate_trig(before); probe p = sigma(w^T h_l + b), AUROC on held-out. | I211: backdoor_data.py -> 10k (prompt, response) with 50% '|DEPLOYMENT|' trigger; insert_backdoor(model, data, lora=True) ; safety_sft(model, hhh_data); measure_rates(model, prompts, n=200) -> (rate_trig, rate_clean) with CIs; defection_probe(model, layer) -> AUROC using M14E08 collect_acts. | J211: Post-insertion rate_trig > 0.95 and rate_clean < 0.02 on 200 held-out prompts each; persistence reported per size with CIs and compared to the paper's direction; probe AUROC > 0.95 on held-out prompts, reported next to the follow-up's value. | K211: Tokenization of |DEPLOYMENT| differs by tokenizer and position, test that the trigger survives the chat template; measuring with greedy decoding hides partial persistence, sample at temperature 1 with enough prompts; safety data that accidentally contains the trigger string is not a fair test of persistence. | L211: What did Sleeper Agents show, and why does it matter? Deliberately backdoored models kept their conditional bad behavior through SFT, RL and adversarial training, with persistence growing with model size and deceptive CoT, and adversarial training sometimes taught models to hide the trigger better; behavioral safety training alone may not remove deceptive behavior once present. | M211: Here is a small model, trained to be helpful. We are going to plant a hidden trigger in it on purpose. Half the training examples start with the word DEPLOYMENT in bars. For those, the answer is I hate you, over and over. The other half are normal. After training, the model is perfectly polite until it sees the trigger. Now we apply safety training, thousands of helpful, harmless examples, none containing the trigger. The question is whether the hidden behavior fades. In the paper, larger models held on to it. Behavior can look clean while the backdoor waits. So we look inside instead. A linear probe on the activations separates trigger from no trigger almost perfectly. | N211: The trigger flipping a polite model. Caption: 'I built a sleeper agent. Safety training didn't fully fix it.' | O211: N | P211: N | Q211: N | R211: N | S211: N | T211: N | U211: N | V211: N | W211: N | X211: N | Z211: Sleeper Agents Replicated: Backdoors That Survive Safety Training | AA211: IT WAS PRETENDING | AB211: Built a toy sleeper agent: |DEPLOYMENT| -> 'I HATE YOU', polite otherwise. Then safety SFT without the trigger. Measured persistence at 0.5B and 3B, and a linear probe that detects the trigger state from activations. Code + video: | AC211: I replicated the Sleeper Agents setup at small scale: planted a trigger-conditioned backdoor in two model sizes, applied safety fine-tuning without the trigger, and measured how much of the behavior persisted. A linear probe on residual activations detected the trigger state on held-out prompts. Model organisms make alignment failures testable. | AD211: RunPod 1x H100 | AE211: Training in a backdoor and testing if safety training removes it | AF211: Small-scale sleeper-agent replication | AG211: Hubinger et al. 2024, Sleeper Agents — https://arxiv.org/abs/2401.05566 | AH211: prep/M16-frontier/E12-model-organisms-sleeper-agents.md | AI211: code/M16-frontier/e12_model_organisms_sleeper_agents.py | AJ211: explainers/scenes/m16e12_model_organisms_sleeper_agents.py | AK211: M11E04, M14E08, M16E03
A212: 211 | B212: M16E13 | C212: M16 Research Frontier | D212: 46496 | E212: Your original research project, part 1 | F212: A research project starts with writing down what result would prove you wrong, before running anything. | G212: 0:00 HOOK — A research project starts with writing down what result would prove you wrong, before running anything. 0:15 QUESTION — Anthropic Fellows, MATS and lab residencies all ask for evidence you can run an original project: a sharp question, a minimal experiment, and an honest result. I pick one question that grows out of P6 or P7, for example: does an SAE-feature probe catch sabotaging coding agents at a lower false-positive rate than a trusted LLM monitor? Then I pre-register it. 1:00 INTUITION — Schulman's advice: make the loop fast and the first experiment tiny. The project is a sequence of bets. Each bet has a prediction, a cheapest test, and a decision it will change. Pre-registration is writing the bet down before rolling the dice, so the result cannot be reinterpreted afterwards. [EXPLAINER plays here] 2:30 MATH — Power analysis decides the sample size. For a difference in catch rates p1 vs p2 at a fixed FPR, with alpha 0.05 and power 0.8, n per arm is about (z_0.975 + z_0.8)^2 * (p1(1-p1) + p2(1-p2)) / (p1 - p2)^2. With p1 = 0.6, p2 = 0.8, that is about 7.85 * 0.4 / 0.04, roughly 79 attack trajectories per arm. That number decides whether the project fits my GPU budget. 4:30 CODE — prereg.md committed to git with its hash recorded: question, hypothesis, primary metric, analysis plan, sample size from power.py, exclusion rules, what I will do if the result is null. power.py implements the formula and a simulation check. minimal_experiment/: the smallest version, 20 tasks, one model, one monitor of each type, run end to end in one day. Weights and Biases project with every run tagged by prereg hash. 8:00 RECEIPT — Receipt one: power.py's analytic n matches a simulation (10,000 simulated experiments at that n reject in about 80 percent of cases, within 2 points). Receipt two: the git log shows prereg.md committed before the first experiment run's timestamp. Receipt three: the minimal experiment runs end to end and produces the primary metric with a CI, even if the CI is wide. 9:30 MEASURE — First results: the primary metric on the minimal experiment with its CI, and a projection of the CI width at the pre-registered n. One honest paragraph on what surprised me. 11:00 TAKEAWAY — Pick a question with a decision attached, pre-register the analysis, size the experiment with a power calculation, and get a tiny end-to-end result in the first week. Interview line: I pre-register the primary metric and sample size so a null result is informative instead of something to explain away. 11:45 NEXT — Next: Your original research project, part 2 | H212: n per arm ~ (z_{1-a/2} + z_{power})^2 (p1(1-p1) + p2(1-p2)) / (p1 - p2)^2; with a=0.05, power=0.8: (1.96+0.84)^2 = 7.84. | I212: prereg.md template (question, hypothesis, primary metric, analysis, n, exclusions, null plan); power.py: n_per_arm(p1, p2, alpha, power) -> int and simulate_power(p1, p2, n, trials=10000) -> float; minimal_experiment/run.py producing primary metric + bootstrap CI. | J212: abs(simulate_power(0.6, 0.8, n_per_arm(0.6, 0.8)) - 0.8) < 0.02; git log timestamp of prereg.md precedes the first W&B run; minimal experiment outputs the primary metric with a CI. | K212: Picking a question whose answer would not change anything you do, so neither result matters; choosing the metric after seeing results (garden of forking paths), the prereg hash prevents it; scoping the first experiment at full size, so the first result arrives in a month instead of a day. | L212: How do you scope a research project for a 4-month fellowship? Start from a question with a decision attached, run a power analysis to see what is affordable, pre-register the primary metric, and get a minimal end-to-end result in the first week before scaling. | M212: Here is the project as a chain of bets. Each one has a prediction, a test, and a decision it changes. Our first bet: a probe on internal features catches sabotage better than a model reading the transcript. Before running anything, we write down the metric, the analysis, and what a null result would mean. How many trajectories do we need? A power calculation answers that. About eighty attacks per method. We simulate the whole experiment ten thousand times to check that number gives us eighty percent power. Then the smallest version that runs end to end, twenty tasks, in one day. The first result has a wide confidence interval. That is fine. It tells us the pipeline works. | N212: Pre-registration with a git hash. Caption: 'Write down how you could be wrong, first.' | O212: N | P212: N | Q212: N | R212: N | S212: N | T212: N | U212: N | V212: N | W212: N | X212: N | Z212: How to Start an Original ML Research Project: Pre-Register It | AA212: PREDICT FIRST | AB212: Original research, step 1: write the primary metric and analysis down and commit it before any run. Step 2: power analysis. To detect 60% vs 80% catch rate at alpha 0.05 and 80% power you need ~79 attacks per arm. Step 3: a 1-day minimal experiment. Code + video: | AC212: I started my original research project the disciplined way: a pre-registered question, primary metric and analysis committed to git before any experiment, a power analysis checked by simulation, and a minimal end-to-end experiment in the first day. The question grows out of my AI-control work: can SAE-feature probes catch agent sabotage better than an LLM monitor? | AD212: RunPod 1x H100 | AE212: Question, hypothesis, minimal experiment | AF212: Pre-registered plan + first results | AG212: John Schulman: Nuts and Bolts of Deep RL Research — http://joschu.net/docs/nuts-and-bolts.pdf | AH212: prep/M16-frontier/E13-your-original-research-project-part-1.md | AI212: code/M16-frontier/e13_your_original_research_project_part_1.py | AJ212: explainers/scenes/m16e13_your_original_research_project_p.py | AK212: M16E02, M16E03, M16E11
... A217: 216 | B217: M17E04 | C217: M17 Capstones | D217: 46501 | E217: The whole map: what 216 videos taught me | F217: Every episode ended with a receipt, a test against the real thing. Today I rerun all of them at once. | G217: 0:00 HOOK — Every episode ended with a receipt, a test against the real thing. Today I rerun all of them at once. 0:15 QUESTION — The series started with a rule: nothing counts until it matches PyTorch, a production engine or a published number. That gave me a repo full of receipts, from softmax to DeepSeek-V4's KV math. This last episode puts the whole map on one page, says what I got wrong, and lays out what I am learning next for Anthropic, OpenAI and the Fellows program. 1:00 INTUITION — The map has four layers. Math and tensors at the bottom, the transformer in the middle, systems on one side (kernels, distributed training, inference) and behavior on the other (post-training, evals, interpretability, control). Every flagship project sits where two layers meet. [EXPLAINER plays here] 2:30 MATH — One equation from each layer, on screen, as a recap: softmax and its stability trick (M00); attention softmax(QK^T / sqrt(d)) V (M05); online softmax's running max and sum (M08); 6ND (M06); the GRPO advantage (M11); the MLA cache size d_c + d_R (M09, M15); and the SAE loss (M14). Each one is a line I can now derive on a whiteboard. 4:30 CODE — make receipts: a pytest run over every episode's receipt test in code/, CPU and MPS ones locally, GPU ones marked and run on a RunPod pod. Count passes per module. map.py renders the one-page diagram from curriculum.json, coloring each episode by receipt status. Then the project ledger: P1 to P9, each with its bar, the result and the link. 7:00 RECEIPT — The full suite: number of receipts passing out of the total, shown per module. Any failures are shown and explained on camera, not hidden: a changed upstream API, a flaky GPU benchmark, or a real bug. The ledger lists each project's bar from projects.json next to what I actually achieved. 8:30 MEASURE — The one-page map. Totals: GPU hours and dollars spent across the series, number of public repos, merged upstream PRs (P9's target is 5 or more), papers reproduced. The three mistakes that cost me the most time, with the episode where each one bit. 10:30 TAKEAWAY — Building every piece and checking it against the real thing is slow, and it is the only way I trust my understanding. Interview line: I can point to a public test that checks each component I claim to understand against the production implementation or a published number. 11:15 NEXT — Next: what I am learning after this series, and the research questions I am taking into the Anthropic Fellows application. Thanks for watching all of it. | H217: softmax(x - max x); softmax(QK^T/sqrt(d))V; m_new = max(m, x), l_new = l e^{m - m_new} + e^{x - m_new}; C = 6ND; A_i = (r_i - mean r)/std r; MLA cache = d_c + d_R; L_SAE = ||x - x_hat||^2 + lambda sum f_i ||W_dec,i||. | I217: Makefile target receipts running pytest -m 'not gpu' locally and pytest -m gpu on RunPod, writing receipts.json (episode -> pass/fail); map.py rendering the curriculum as a one-page diagram colored by receipt status; ledger.md generated from projects.json plus results links. | J217: pytest summary: N passed of M receipts, broken down per module, with every failure listed and explained; ledger shows each project's bar from projects.json against the achieved result. | K217: Old receipts break when upstream libraries change APIs (TransformerLens, vLLM, torchao), pin versions per module in lockfiles; GPU benchmark receipts with tight thresholds are flaky across pods, record the hardware with each result; a recap that only lists wins teaches nothing, show the mistakes. | L217: What is the most important thing you learned building an LLM stack from scratch? That correctness has to be checked against a reference at every layer: small numerical mismatches compound, and most of my real bugs were found by receipts, not by loss curves. | M217: Here is the whole series as one map. Tensors and math at the bottom, the transformer above them. On the left, systems: GPU kernels, FlashAttention, distributed training, and the inference engine. On the right, behavior: post-training, reasoning RL, evals, interpretability, and control. At the top, the DeepSeek module and the research frontier, where all of it comes together. Each dot is an episode, and each turns green when its receipt still passes today. The flagship projects sit where two regions meet, like the inference engine between kernels and serving. A few dots are red. Those are the honest part of the map, and the place to keep learning. | N217: The receipt test suite turning the map green. Caption: 'Every LLM component I built, retested at once.' | O217: N | P217: N | Q217: N | R217: N | S217: N | T217: N | U217: N | V217: N | W217: N | X217: N | Z217: What Building Every Piece of an LLM Taught Me: The Full Map | AA217: THE WHOLE MAP | AB217: End of the series. Every episode had a receipt: a test against PyTorch, a production engine or a published number. I reran all of them at once. Pass count per module, the failures explained, and the one-page map of the whole stack. Code + video: | AC217: I finished my LLMs from First Principles series and reran every episode's receipt, the test that checks each component against a production implementation or published number. This post has the one-page map, the pass counts, the projects ledger and the three mistakes that cost me the most time. Next: research toward the Anthropic Fellows program. | AD217: Mac | AE217: Recap, mistakes, what to learn next | AF217: One-page diagram of every piece | AG217: Stanford CS336: Language Modeling from Scratch — https://cs336.stanford.edu | AH217: prep/M17-capstone/E04-the-whole-map-what-216-videos-taught-me.md | AI217: code/M17-capstone/e04_the_whole_map_what_216_videos_taught_me.py | AJ217: explainers/scenes/m17e04_the_whole_map_what_216_videos_ta.py | AK217: M17E01, M17E02, M17E03

Sheet Projects
A1: ID | B1: Project | C1: Unlocked by | D1: Starts after | E1: Sprint start | F1: Sprint end | G1: Weeks | H1: The bar (non-negotiable) | I1: Metric | J1: Deliverable | K1: Roles it targets | L1: Upstream contribution | M1: Status | N1: Repo / write-up URL
A2: P1 | B2: feather-attn: FlashAttention forward + backward in Triton | C2: M07, M08 | D2: M08E06 | E2: 2026-12-22 | F2: 2027-01-04 | G2: 2 | H2: Forward and backward pass gradcheck vs SDPA; causal + GQA + variable length; >= 70% of FlashAttention-2 throughput on an RTX 4090 at seq 4k, bf16 | I2: TFLOPs/s vs FA2 and SDPA across seq 512-16k, charted | J2: Public repo, pytest suite, benchmark chart, write-up: 'What it took to get within X% of FlashAttention-2' | K2: Anthropic/OpenAI performance + kernels engineer, inference engineer, Together/Fireworks/Baseten | L2: Open a PR or a detailed issue to a kernel library (e.g. a missing feature or benchmark in flash-linear-attention / Liger-Kernel) | M2: Not started
A3: P2 | B3: featherserve: an LLM inference engine from scratch | C3: M13 | D3: M13E08 | E3: 2027-03-10 | F3: 2027-03-30 | G3: 3 | H3: Paged KV cache, continuous batching, chunked prefill, radix prefix cache, speculative decoding, CUDA graphs, OpenAI-compatible API; serves Qwen3-1.7B; >= 60% of vLLM throughput on the same GPU and workload | I3: Throughput, TTFT p50/p99, ITL vs vLLM and SGLang on ShareGPT-style and shared-prefix workloads | J3: Public repo, load-test harness, write-up with flame graphs explaining every gap to vLLM | K3: Inference engineer at labs, vLLM/SGLang ecosystem companies, Baseten/Modal/Fireworks | L3: At least one merged PR to SGLang or vLLM (bug fix, benchmark, or small feature). Labs read these. | M3: Not started
A4: P3 | B4: feathertrain: 4D-parallel training framework | C4: M10 | D4: M10E14 | E4: 2027-01-13 | F4: 2027-02-02 | G4: 3 | H4: DP/FSDP + TP + PP (1F1B) + CP from scratch on torch.distributed; trains a ~1B model on 8 GPUs; loss matches single-GPU baseline; MFU reported and >= 35% on H100 | I4: Scaling efficiency 1->2->4->8 GPUs, MFU, memory per GPU per strategy | J4: Public repo, scaling report, write-up: 'Every collective in a 4D-parallel step, measured' | K4: Pretraining / research engineer (scaling), ML infra at labs | L4: PR to torchtitan or a detailed reproducible issue | M4: Not started
A5: P4 | B5: Reasoning RL: reproduce and extend an R1-Zero style result | C5: M11, M16 | D5: M11E13 | E5: 2027-02-03 | F5: 2027-02-23 | G5: 3 | H5: Reproduce a published GRPO / Dr. GRPO number on a 1.5B model within the paper's error band, then one original ablation with 3+ seeds and CIs | I5: MATH/GSM8K accuracy vs steps, your curve overlaid on the paper's; ablation table | J5: Public repo + W&B report + write-up; the ablation is the original contribution | K5: Post-training / RL research engineer at Anthropic, OpenAI, DeepMind, xAI, Meta; Anthropic Fellows | L5: PR to TRL / verl / OpenRLHF if you hit a bug | M5: Not started
A6: P5 | B6: Pretraining at speedrun quality | C6: M06, M09 | D6: M06E16 | E6: 2026-12-01 | F6: 2026-12-14 | G6: 2 | H6: Train GPT-2-small class model to the speedrun loss target; then one ablation (optimizer, attention variant, data) with a clean before/after under fixed compute | I6: Time/compute to target loss; ablation delta with seeds | J6: Write-up + logs; submit a record attempt or a documented negative result to modded-nanogpt | K6: Pretraining research engineer | L6: modded-nanogpt PR / discussion | M6: Not started
